{
  "checks": {
    "completion_flag_matches": true,
    "gate_profile_matches": true,
    "inputs_pass": true,
    "integrity_and_nonhardness_match": true,
    "mandate_and_transport_match": true,
    "native_integrity_flags_match": true,
    "route_selection_matches": true,
    "tool_profile_matches": true
  },
  "claim": "The K23 surface has a certified open-source integrity tooling route: deterministic public verification, mandate audit, invalid-byte rejection, and nonhardness guardrails are explicit.",
  "schema": "long.k23osint.seam@1",
  "status": "SECTOR33_K23_OPEN_SOURCE_INTEGRITY_ROUTE_CERTIFIED",
  "witness": {
    "boundary": "This selects integrity-only tooling as the open-source K23 route and keeps hardness/deployment security unclaimed.",
    "classification": "sector33_k23_open_source_integrity_route",
    "matrix_sha256": "f2aa2155d6cbc503018516c66d9e9f31373842261a9e90e8641bb8198ae1bf0c",
    "name": "long_k23osint",
    "route_code_map": {
      "0": "reduction_source_insertion",
      "1": "integrity_only_tooling",
      "2": "external_benchmark_epoch_ingestion"
    },
    "summary": {
      "blocking_gate_count": 2,
      "bounded_soundness_error_denominator": 112869680,
      "bounded_soundness_error_numerator": 0,
      "certified_input_count": 6,
      "claim_gate_count": 0,
      "complete_goal_claim_flag": 0,
      "deploy_ready_flag": 0,
      "deploy_security_claim_count": 0,
      "deterministic_tool_count": 5,
      "external_route_selected_flag": 0,
      "gate_row_count": 6,
      "hardness_claim_count": 0,
      "input_report_count": 6,
      "integrity_check_tool_count": 5,
      "integrity_route_selected_flag": 1,
      "integrity_tooling_ready_flag": 1,
      "invalid_reject_count": 200,
      "ledger_row_count": 12,
      "mandate_row_count": 56,
      "materialized_reduction_count": 0,
      "native_singularity_theory_flag": 1,
      "open_source_integrity_route_flag": 1,
      "open_tool_boundary_count": 1,
      "proof_of_mandate_flag": 1,
      "proof_of_mandate_ledger_flag": 1,
      "public_table_trivial_problem_count": 2,
      "public_tool_count": 5,
      "reduction_route_selected_flag": 0,
      "rejection_feedback_tool_count": 3,
      "route_blocking_count": 2,
      "route_row_count": 3,
      "satisfied_gate_count": 4,
      "saved_vs_baseline_bytes": 1512,
      "saved_vs_baseline_den": 28,
      "saved_vs_baseline_num": 27,
      "selected_route_count": 1,
      "tool_row_count": 6,
      "transcript_index_bytes": 56,
      "valid_decode_count": 56
    },
    "tool_code_map": {
      "0": "transcript_index_verifier",
      "1": "bounded_tamper_rejector",
      "2": "nonhardness_label_guard",
      "3": "reduction_aperture_placeholder",
      "4": "epoch_manifest_loader",
      "5": "invalid_byte_rejector"
    }
  }
}
