{
  "certified_reading": [
    "radius-three local edits around the two certified oversplitters contain 203866 prefix-valid words",
    "after delta2, sub-223, repair-chord, and closed-positive filters, 219 candidates remain",
    "none has the requested exact 24 closures, six templates, and all-four lift profile",
    "the best all-four rows are still 28-closure seven-template oversplitters, while the closest six-template rows have at least 32 closures"
  ],
  "checks": {
    "best_all_four_ge24_rows_are_28_by_7": true,
    "best_six_template_gap_is_32_closures": true,
    "closed_positive_candidate_count_is_219": true,
    "exact24_rows_exist_but_never_have_six_templates": true,
    "frontier_table_shape_matches_codebook": true,
    "metric_repair_candidate_count_is_10792": true,
    "neighborhood_total_word_count_is_203866": true,
    "no_exact24_six_all_four_trim_exists": true,
    "no_exact24_six_template_trim_exists": true,
    "observable_table_shape_matches_codebook": true,
    "partial_splitter_certificate_certified": true,
    "partial_splitter_declares_seed_oversplitters": true,
    "partial_splitter_report_certified": true,
    "partial_splitter_schema_available": true,
    "profile_table_shape_matches_codebook": true,
    "radius_shell_counts_are_expected": true,
    "shell_table_shape_matches_codebook": true,
    "six_template_rows_exist_but_never_have_24_closures": true,
    "trace_valid_word_count_is_139238": true
  },
  "schema": "c985.d20_signature_boundary_spine_aperture_closure_tail_trim_neighborhood_search_certificate@1",
  "status": "C985_D20_SIGNATURE_BOUNDARY_SPINE_APERTURE_CLOSURE_TAIL_TRIM_NEIGHBORHOOD_SEARCH_CERTIFIED",
  "witness": {
    "best_all_four_ge24_profiles": [
      {
        "closed_paths": 28,
        "edit_radius": 0,
        "template_count": 7,
        "variation": 219,
        "word": [
          2,
          1,
          4,
          3,
          1,
          5,
          5,
          2,
          1,
          4,
          5
        ]
      },
      {
        "closed_paths": 28,
        "edit_radius": 0,
        "template_count": 7,
        "variation": 217,
        "word": [
          2,
          1,
          4,
          3,
          1,
          5,
          2,
          5,
          5,
          2,
          1,
          4,
          5
        ]
      },
      {
        "closed_paths": 28,
        "edit_radius": 1,
        "template_count": 7,
        "variation": 219,
        "word": [
          2,
          1,
          4,
          3,
          1,
          5,
          2,
          1,
          5,
          5,
          2,
          1,
          4,
          5
        ]
      },
      {
        "closed_paths": 28,
        "edit_radius": 3,
        "template_count": 7,
        "variation": 219,
        "word": [
          2,
          1,
          5,
          2,
          1,
          4,
          3,
          1,
          5,
          5,
          2,
          1,
          4,
          5
        ]
      },
      {
        "closed_paths": 28,
        "edit_radius": 2,
        "template_count": 7,
        "variation": 217,
        "word": [
          2,
          1,
          4,
          3,
          1,
          5,
          2,
          5,
          2,
          5,
          5,
          2,
          1,
          4,
          5
        ]
      },
      {
        "closed_paths": 28,
        "edit_radius": 3,
        "template_count": 7,
        "variation": 217,
        "word": [
          2,
          1,
          4,
          3,
          1,
          5,
          2,
          1,
          5,
          2,
          5,
          5,
          2,
          1,
          4,
          5
        ]
      },
      {
        "closed_paths": 28,
        "edit_radius": 3,
        "template_count": 7,
        "variation": 221,
        "word": [
          2,
          1,
          4,
          3,
          1,
          5,
          4,
          1,
          5,
          2,
          5,
          5,
          2,
          1,
          4,
          5
        ]
      },
      {
        "closed_paths": 28,
        "edit_radius": 3,
        "template_count": 7,
        "variation": 217,
        "word": [
          2,
          1,
          5,
          2,
          1,
          4,
          3,
          1,
          5,
          2,
          5,
          5,
          2,
          1,
          4,
          5
        ]
      }
    ],
    "best_six_template_closure_excess": 8,
    "closed_positive_candidate_count": 219,
    "exact24_count": 14,
    "exact24_six_all_four_count": 0,
    "exact24_six_template_count": 0,
    "frontier_table_sha256": "de43127be8644e95a7b5c7cc63b1d7b898e3e04d41afaba189d9a63ad7bdcf93",
    "neighborhood_shell_counts": [
      2,
      185,
      7712,
      195967
    ],
    "observable_table_sha256": "d0da3abdf4655c60fec316fac77554a869a9db0d42fd78e36ebfcd7cc4ffb8bc",
    "profile_table_sha256": "531bb9c9ade284856f62cafd6a2d8884e4ca496f5a9f388c064a34195f09cbd6",
    "seed_partial_candidate_ids": [
      19,
      20
    ],
    "seed_words": [
      [
        2,
        1,
        4,
        3,
        1,
        5,
        2,
        5,
        5,
        2,
        1,
        4,
        5
      ],
      [
        2,
        1,
        4,
        3,
        1,
        5,
        5,
        2,
        1,
        4,
        5
      ]
    ],
    "shell_table_sha256": "80a7ac0554ed85b749fc41a59ada9b1938bbdcc7efa9660dc3b05ccee086321a",
    "six_template_count": 37
  }
}
