{
  "checks": {
    "boundary_flags_match": true,
    "family_profile_matches": true,
    "inputs_pass": true,
    "product_family_obstructed": true,
    "quotient_and_unit_residuals_zero": true
  },
  "schema": "long.k23fam.cert@1",
  "status": "SECTOR33_K23_MINIMAL_REPAIRED_PROJECTION_FAMILY_OBSTRUCTED",
  "witness": {
    "boundary": "This certifies that all 24 rank-restoring unit-entry minimal repaired projections have exact quotient and unit behavior, but none preserve the closure60 product.",
    "classification": "sector33_k23_minimal_repaired_projection_family_obstruction",
    "matrix_sha256": "bb527da75e9f239db51e42a2be40c67ce23310db51304fb4097ee11ec6d01e4a",
    "name": "long_k23fam",
    "summary": {
      "appended_column_count": 4,
      "best_candidate_id": 10,
      "best_candidate_product_residual_total": 958530,
      "candidate_generator_row_count": 216,
      "closure_dimension": 60,
      "complete_goal_claim_flag": 0,
      "fixed_target_row_count": 3,
      "generator_count": 9,
      "long_k23cl_certified_flag": 1,
      "long_k23proj_certified_flag": 1,
      "long_k23rh_certified_flag": 1,
      "long_k23tgt_certified_flag": 1,
      "long_k23unit_certified_flag": 1,
      "old_unit_column_count": 2,
      "product_obstructed_candidate_count": 24,
      "product_preserved_candidate_count": 0,
      "product_residual_total_max": 1014453,
      "product_residual_total_min": 958530,
      "quotient_residual_total": 0,
      "rank_restoring_candidate_count": 24,
      "raw_candidate_count": 792,
      "target_dimension": 33,
      "unit_residual_total": 0
    }
  }
}
