{
  "character_table": "data/invariants/d20/theorems/tiny_pointer_a985_canonical_sector_characters/canonical_sector_character_table.npz",
  "field_prime": 1000003,
  "input_schema": "d20.tiny_pointer_a985.burning_static_representative_input@1",
  "linear_rule": "For each representative/generator vector v=sum_alpha c_alpha R_alpha, the source-sector trace is tr_s(v)=sum_alpha c_alpha chi_s(R_alpha) modulo 1000003.",
  "output_profile_columns": [
    "representative_id",
    "quotient_generator",
    "source_sector",
    "raw_sector",
    "block_dimension",
    "trace_mod_1000003",
    "trace_signed",
    "sector_in_support"
  ],
  "required_csv_columns": [
    "representative_id",
    "quotient_generator",
    "relation_alpha",
    "coefficient_mod_1000003",
    "source_artifact",
    "source_row"
  ],
  "schema": "d20.tiny_pointer_a985.burning_static_trace_evaluator_contract@1"
}
