{
  "all_checks_pass": true,
  "certificate_sha256": "b668840c0cbd184298783389484a44175ab5d206e984bac84a46a6914a420da5",
  "checks": {
    "all_profile_hessians_nonpositive_at_equality": true,
    "exhaustive_two_level_input_certified": true,
    "full_arbitrary_vector_theorem_not_certified": true,
    "full_three_level_exhaustion_not_certified": true,
    "generated_code_has_4096_words": true,
    "generated_code_weight_histogram_matches_w24": true,
    "no_positive_structured_three_level_profile_found": true,
    "profile_csv_written": true,
    "selected_partitions_nonempty": true,
    "unique_profiles_nonempty": true,
    "w24_endpoint_certified": true
  },
  "claim": "The structured three-level probe found no counterexample for w=12 or w=16. It tested prefix flags, MOG/W24 structural partitions, W24 codeword support splits, representative codeword-pair flags, and deterministic ternary random partitions. Every selected profile has nonpositive Hessian at equality and numerical ascent returned no positive objective. This is a diagnostic bridge beyond the exhaustive two-level theorem, not a full three-level theorem.",
  "inputs": {
    "artifact": {
      "artifact_sha256_excluding_this_field": "c682c5f7b3b97255932feea5367c0722f5c4af3468679d017f59978251f4064a",
      "path": "generated/d20_golay_shell_three_level_structured_probe.json",
      "schema": "d20.proof_obligation.golay_shell_three_level_structured_probe.artifact@1",
      "sha256": "c3387d0d4602f4038fc266fa11692cefc1400b1f3f26aabf7b3ee2d81da77fe3",
      "status": "D20_GOLAY_SHELL_THREE_LEVEL_STRUCTURED_PROBE_NO_COUNTEREXAMPLE"
    },
    "derive_script": {
      "path": "src/derive_d20_golay_shell_three_level_structured_probe.py",
      "sha256": "5129316479ca149722a3c4881d02cb07653eda37a61fdcd84e8b0dbf9597374e"
    },
    "exhaustive_two_level_sos": {
      "certificate_sha256": "5d3b36d10878097a70b9fb777420bd34bcac18841c14575dbfc522d0afcffbfe",
      "path": "data/invariants/d20/proof_obligations/d20_golay_shell_exhaustive_two_level_sos/report.json",
      "sha256": "42a51ae5cdfc780a5a366381ec075306de98a843d5adf549cee75e42e615ebd8",
      "status": "D20_GOLAY_SHELL_EXHAUSTIVE_TWO_LEVEL_SOS_CERTIFIED"
    },
    "validator": {
      "path": "src/certify_d20_golay_shell_three_level_structured_probe.py",
      "sha256": "3d5ef3d1745a822c630226fe7d51daa1c2b45c0ed27991e3a4851a7fbf34c608"
    },
    "w24_row_alphabetization": {
      "certificate_sha256": "ecd1f8bbe2a0412335a9e3a4955124032eba6ae781aa28e56b1d62ce3b6caca9",
      "path": "data/invariants/d20/proof_obligations/d20_w24_hexacode_row_alphabetization/report.json",
      "sha256": "757fb8ab288ad8932d7b70b6bda5479e5cba4c026e48237317638701139d4bb9",
      "status": "D20_W24_HEXACODE_ROW_ALPHABETIZATION_CERTIFIED"
    }
  },
  "next_highest_yield_item": "Derive actual M24/Terwilliger orbit representatives for ordered three-colorings. That would replace this structured probe with an exhaustive three-level profile certificate.",
  "schema": "d20.proof_obligation.golay_shell_three_level_structured_probe@1",
  "status": "D20_GOLAY_SHELL_THREE_LEVEL_STRUCTURED_PROBE_CERTIFIED_NO_COUNTEREXAMPLE",
  "witness": {
    "definition": {
      "edge_boundary": "The u=0, v=0, u=v, and level-empty faces reduce to the exhaustive two-level certificate already proved.",
      "objective": "F_w(A,B,u,v)=log(sum_{block} exp(u|block cap A|+v|block cap B|))-log(A_w)-(w/2)log((|A|exp(2u)+|B|exp(2v)+24-|A|-|B|)/24)",
      "three_level_vector": "x_i=exp(u) on A, x_i=exp(v) on B, and x_i=1 off A union B, with A cap B empty."
    },
    "open_boundary": {
      "certified_here": [
        "no positive maximum found in the selected structured three-level profile family",
        "all selected profiles have nonpositive Hessian at the equality point",
        "all one-dimensional faces are covered by the exhaustive two-level certificate"
      ],
      "not_certified": [
        "all 3^24 ordered three-level partitions",
        "a bivariate positive-coefficient/SOS certificate for every three-level profile",
        "four-level or arbitrary nonnegative vectors",
        "the full w=12 entropy contraction theorem",
        "the full w=16 entropy contraction theorem"
      ]
    },
    "selection": {
      "included_families": [
        "all prefix flags A subset A union B",
        "all pairwise structural MOG/W24 mask flags and symmetric differences",
        "all W24 codeword supports split by MOG rows, columns, row-pairs, column-pair codewords, and Wu octad",
        "representative codeword-pair flags by shell weight",
        "deterministic ternary random partitions"
      ],
      "local_hessian_positive_count": 0,
      "max_best_F": 1.4210854715202004e-14,
      "positive_profile_count": 0,
      "selected_partition_count": 234851,
      "top_profiles": [
        {
          "best_F": 1.4210854715202004e-14,
          "best_gradient_norm": 1.9777601356788236e-08,
          "best_u": -5.9999999901283205,
          "best_v": -6.000000009871675,
          "example_labels": "prefix_flag_1_24;struct_flag:full:prefix_1;struct_flag:prefix_24:prefix_1",
          "first_size": 1,
          "hessian_max_eigenvalue_at_equality": 0.0,
          "hessian_min_eigenvalue_at_equality": -1.4166666666666667,
          "local_hessian_nonpositive": true,
          "partition_count": 2,
          "profile": "0,0,0,0,0,0,0,0,0,0,0,0,1288,0,0,0,0,0,0,0,0,0,0,0,1288,0,0,0,0,0,0,0,0,0,0,0,0,0,0,0,0,0,0,0,0,0,0,0,0,0,0,0,0,0,0,0,0,0,0,0,0,0,0,0,0,0,0,0,0,0,0,0,0,0,0,0,0,0,0,0,0,0,0,0,0,0,0,0,0,0,0,0,0,0,0,0,0,0,0,0,0,0,0,0,0,0,0,0,0,0,0,0,0,0,0,0,0,0,0,0,0,0,0,0,0,0,0,0,0,0,0,0,0,0,0,0,0,0,0,0,0,0,0,0,0,0,0,0,0,0,0,0,0,0,0,0,0,0,0,0,0,0,0,0,0,0,0,0,0",
          "rest_size": 0,
          "second_size": 23,
          "shell": 12
        },
        {
          "best_F": 1.4210854715202004e-14,
          "best_gradient_norm": 2.9476039550728006e-08,
          "best_u": -5.999999992309375,
          "best_v": -6.0000000076906215,
          "example_labels": "prefix_flag_2_24;struct_flag:full:prefix_2;struct_flag:prefix_24:prefix_2",
          "first_size": 2,
          "hessian_max_eigenvalue_at_equality": -6.661338147750939e-16,
          "hessian_min_eigenvalue_at_equality": -2.7101449275362297,
          "local_hessian_nonpositive": true,
          "partition_count": 2,
          "profile": "0,0,0,0,0,0,0,0,0,0,0,0,616,0,0,0,0,0,0,0,0,0,0,0,1344,0,0,0,0,0,0,0,0,0,0,0,616,0,0,0,0,0,0,0,0,0,0,0,0,0,0,0,0,0,0,0,0,0,0,0,0,0,0,0,0,0,0,0,0,0,0,0,0,0,0,0,0,0,0,0,0,0,0,0,0,0,0,0,0,0,0,0,0,0,0,0,0,0,0,0,0,0,0,0,0,0,0,0,0,0,0,0,0,0,0,0,0,0,0,0,0,0,0,0,0,0,0,0,0,0,0,0,0,0,0,0,0,0,0,0,0,0,0,0,0,0,0,0,0,0,0,0,0,0,0,0,0,0,0,0,0,0,0,0,0,0,0,0,0",
          "rest_size": 0,
          "second_size": 22,
          "shell": 12
        },
        {
          "best_F": 1.4210854715202004e-14,
          "best_gradient_norm": 6.726558050205023e-08,
          "best_u": -6.000000007150139,
          "best_v": -5.999999992849866,
          "example_labels": "codeword_w24_split_by_mog_row_0;prefix_flag_6_24;struct_flag:full:mog_row_0;struct_flag:full:prefix_6;struct_flag:full:w24_row_mask_0;struct_flag:prefix_24:mog_row_0;struct_flag:prefix_24:prefix_6;struct_flag:prefix_24:w24_row_mask_0",
          "first_size": 6,
          "hessian_max_eigenvalue_at_equality": 8.881784197001252e-16,
          "hessian_min_eigenvalue_at_equality": -6.652173913043476,
          "local_hessian_nonpositive": true,
          "partition_count": 4,
          "profile": "0,0,0,0,0,0,0,0,0,0,0,0,18,0,0,0,0,0,0,0,0,0,0,0,180,0,0,0,0,0,0,0,0,0,0,0,630,0,0,0,0,0,0,0,0,0,0,0,920,0,0,0,0,0,0,0,0,0,0,0,630,0,0,0,0,0,0,0,0,0,0,0,180,0,0,0,0,0,0,0,0,0,0,0,18,0,0,0,0,0,0,0,0,0,0,0,0,0,0,0,0,0,0,0,0,0,0,0,0,0,0,0,0,0,0,0,0,0,0,0,0,0,0,0,0,0,0,0,0,0,0,0,0,0,0,0,0,0,0,0,0,0,0,0,0,0,0,0,0,0,0,0,0,0,0,0,0,0,0,0,0,0,0,0,0,0,0,0,0",
          "rest_size": 0,
          "second_size": 18,
          "shell": 12
        },
        {
          "best_F": 1.4210854715202004e-14,
          "best_gradient_norm": 1.4928454609678826e-07,
          "best_u": -5.9999999855983255,
          "best_v": -6.000000014401678,
          "example_labels": "prefix_flag_7_24;struct_flag:full:prefix_7;struct_flag:prefix_24:prefix_7",
          "first_size": 7,
          "hessian_max_eigenvalue_at_equality": -1.7763568394002505e-15,
          "hessian_min_eigenvalue_at_equality": -7.329710144927535,
          "local_hessian_nonpositive": true,
          "partition_count": 2,
          "profile": "0,0,0,0,0,0,0,0,0,0,0,0,6,0,0,0,0,0,0,0,0,0,0,0,82,0,0,0,0,0,0,0,0,0,0,0,390,0,0,0,0,0,0,0,0,0,0,0,810,0,0,0,0,0,0,0,0,0,0,0,810,0,0,0,0,0,0,0,0,0,0,0,390,0,0,0,0,0,0,0,0,0,0,0,82,0,0,0,0,0,0,0,0,0,0,0,6,0,0,0,0,0,0,0,0,0,0,0,0,0,0,0,0,0,0,0,0,0,0,0,0,0,0,0,0,0,0,0,0,0,0,0,0,0,0,0,0,0,0,0,0,0,0,0,0,0,0,0,0,0,0,0,0,0,0,0,0,0,0,0,0,0,0,0,0,0,0,0,0",
          "rest_size": 0,
          "second_size": 17,
          "shell": 12
        },
        {
          "best_F": 1.4210854715202004e-14,
          "best_gradient_norm": 2.0920576696649625e-07,
          "best_u": -6.000000017790371,
          "best_v": -5.9999999822096255,
          "example_labels": "prefix_flag_9_24;struct_flag:full:prefix_9;struct_flag:prefix_24:prefix_9",
          "first_size": 9,
          "hessian_max_eigenvalue_at_equality": 1.7763568394002505e-14,
          "hessian_min_eigenvalue_at_equality": -8.315217391304355,
          "local_hessian_nonpositive": true,
          "partition_count": 2,
          "profile": "0,0,0,0,0,0,0,0,0,0,0,0,1,0,0,0,0,0,0,0,0,0,0,0,9,0,0,0,0,0,0,0,0,0,0,0,108,0,0,0,0,0,0,0,0,0,0,0,396,0,0,0,0,0,0,0,0,0,0,0,774,0,0,0,0,0,0,0,0,0,0,0,774,0,0,0,0,0,0,0,0,0,0,0,396,0,0,0,0,0,0,0,0,0,0,0,108,0,0,0,0,0,0,0,0,0,0,0,9,0,0,0,0,0,0,0,0,0,0,0,1,0,0,0,0,0,0,0,0,0,0,0,0,0,0,0,0,0,0,0,0,0,0,0,0,0,0,0,0,0,0,0,0,0,0,0,0,0,0,0,0,0,0,0,0,0,0,0,0",
          "rest_size": 0,
          "second_size": 15,
          "shell": 12
        },
        {
          "best_F": 1.4210854715202004e-14,
          "best_gradient_norm": 3.378995101081575e-08,
          "best_u": -5.999999997229201,
          "best_v": -6.000000002770795,
          "example_labels": "prefix_flag_10_24;struct_flag:full:prefix_10;struct_flag:prefix_24:prefix_10",
          "first_size": 10,
          "hessian_max_eigenvalue_at_equality": 0.0,
          "hessian_min_eigenvalue_at_equality": -8.623188405797103,
          "local_hessian_nonpositive": true,
          "partition_count": 2,
          "profile": "0,0,0,0,0,0,0,0,0,0,0,0,1,0,0,0,0,0,0,0,0,0,0,0,0,0,0,0,0,0,0,0,0,0,0,0,45,0,0,0,0,0,0,0,0,0,0,0,240,0,0,0,0,0,0,0,0,0,0,0,570,0,0,0,0,0,0,0,0,0,0,0,864,0,0,0,0,0,0,0,0,0,0,0,570,0,0,0,0,0,0,0,0,0,0,0,240,0,0,0,0,0,0,0,0,0,0,0,45,0,0,0,0,0,0,0,0,0,0,0,0,0,0,0,0,0,0,0,0,0,0,0,1,0,0,0,0,0,0,0,0,0,0,0,0,0,0,0,0,0,0,0,0,0,0,0,0,0,0,0,0,0,0,0,0,0,0,0,0",
          "rest_size": 0,
          "second_size": 14,
          "shell": 12
        },
        {
          "best_F": 1.4210854715202004e-14,
          "best_gradient_norm": 1.9398959963375935e-07,
          "best_u": -5.99999998442645,
          "best_v": -6.000000015573547,
          "example_labels": "prefix_flag_11_24;struct_flag:full:prefix_11;struct_flag:prefix_24:prefix_11",
          "first_size": 11,
          "hessian_max_eigenvalue_at_equality": 5.329070518200751e-15,
          "hessian_min_eigenvalue_at_equality": -8.807971014492754,
          "local_hessian_nonpositive": true,
          "partition_count": 2,
          "profile": "0,0,0,0,0,0,0,0,0,0,0,0,1,0,0,0,0,0,0,0,0,0,0,0,0,0,0,0,0,0,0,0,0,0,0,0,0,0,0,0,0,0,0,0,0,0,0,0,165,0,0,0,0,0,0,0,0,0,0,0,330,0,0,0,0,0,0,0,0,0,0,0,792,0,0,0,0,0,0,0,0,0,0,0,792,0,0,0,0,0,0,0,0,0,0,0,330,0,0,0,0,0,0,0,0,0,0,0,165,0,0,0,0,0,0,0,0,0,0,0,0,0,0,0,0,0,0,0,0,0,0,0,0,0,0,0,0,0,0,0,0,0,0,0,1,0,0,0,0,0,0,0,0,0,0,0,0,0,0,0,0,0,0,0,0,0,0,0,0",
          "rest_size": 0,
          "second_size": 13,
          "shell": 12
        },
        {
          "best_F": 1.4210854715202004e-14,
          "best_gradient_norm": 1.9398959963375935e-07,
          "best_u": -6.000000015573547,
          "best_v": -5.99999998442645,
          "example_labels": "prefix_flag_13_24;struct_flag:full:prefix_13;struct_flag:prefix_24:prefix_13",
          "first_size": 13,
          "hessian_max_eigenvalue_at_equality": 5.329070518200751e-15,
          "hessian_min_eigenvalue_at_equality": -8.807971014492754,
          "local_hessian_nonpositive": true,
          "partition_count": 2,
          "profile": "0,0,0,0,0,0,0,0,0,0,0,0,0,0,0,0,0,0,0,0,0,0,0,0,1,0,0,0,0,0,0,0,0,0,0,0,0,0,0,0,0,0,0,0,0,0,0,0,0,0,0,0,0,0,0,0,0,0,0,0,165,0,0,0,0,0,0,0,0,0,0,0,330,0,0,0,0,0,0,0,0,0,0,0,792,0,0,0,0,0,0,0,0,0,0,0,792,0,0,0,0,0,0,0,0,0,0,0,330,0,0,0,0,0,0,0,0,0,0,0,165,0,0,0,0,0,0,0,0,0,0,0,0,0,0,0,0,0,0,0,0,0,0,0,0,0,0,0,0,0,0,0,0,0,0,0,1,0,0,0,0,0,0,0,0,0,0,0,0",
          "rest_size": 0,
          "second_size": 11,
          "shell": 12
        },
        {
          "best_F": 1.4210854715202004e-14,
          "best_gradient_norm": 3.378995101081575e-08,
          "best_u": -6.000000002770795,
          "best_v": -5.999999997229201,
          "example_labels": "prefix_flag_14_24;struct_flag:full:prefix_14;struct_flag:prefix_24:prefix_14",
          "first_size": 14,
          "hessian_max_eigenvalue_at_equality": -5.329070518200751e-15,
          "hessian_min_eigenvalue_at_equality": -8.623188405797094,
          "local_hessian_nonpositive": true,
          "partition_count": 2,
          "profile": "0,0,0,0,0,0,0,0,0,0,0,0,0,0,0,0,0,0,0,0,0,0,0,0,0,0,0,0,0,0,0,0,0,0,0,0,1,0,0,0,0,0,0,0,0,0,0,0,0,0,0,0,0,0,0,0,0,0,0,0,45,0,0,0,0,0,0,0,0,0,0,0,240,0,0,0,0,0,0,0,0,0,0,0,570,0,0,0,0,0,0,0,0,0,0,0,864,0,0,0,0,0,0,0,0,0,0,0,570,0,0,0,0,0,0,0,0,0,0,0,240,0,0,0,0,0,0,0,0,0,0,0,45,0,0,0,0,0,0,0,0,0,0,0,0,0,0,0,0,0,0,0,0,0,0,0,1,0,0,0,0,0,0,0,0,0,0,0,0",
          "rest_size": 0,
          "second_size": 10,
          "shell": 12
        },
        {
          "best_F": 1.4210854715202004e-14,
          "best_gradient_norm": 2.0920576696649625e-07,
          "best_u": -5.9999999822096255,
          "best_v": -6.000000017790371,
          "example_labels": "prefix_flag_15_24;struct_flag:full:prefix_15;struct_flag:prefix_24:prefix_15",
          "first_size": 15,
          "hessian_max_eigenvalue_at_equality": 8.881784197001252e-15,
          "hessian_min_eigenvalue_at_equality": -8.31521739130435,
          "local_hessian_nonpositive": true,
          "partition_count": 2,
          "profile": "0,0,0,0,0,0,0,0,0,0,0,0,0,0,0,0,0,0,0,0,0,0,0,0,0,0,0,0,0,0,0,0,0,0,0,0,0,0,0,0,0,0,0,0,0,0,0,0,1,0,0,0,0,0,0,0,0,0,0,0,9,0,0,0,0,0,0,0,0,0,0,0,108,0,0,0,0,0,0,0,0,0,0,0,396,0,0,0,0,0,0,0,0,0,0,0,774,0,0,0,0,0,0,0,0,0,0,0,774,0,0,0,0,0,0,0,0,0,0,0,396,0,0,0,0,0,0,0,0,0,0,0,108,0,0,0,0,0,0,0,0,0,0,0,9,0,0,0,0,0,0,0,0,0,0,0,1,0,0,0,0,0,0,0,0,0,0,0,0",
          "rest_size": 0,
          "second_size": 9,
          "shell": 12
        },
        {
          "best_F": 1.4210854715202004e-14,
          "best_gradient_norm": 1.4928454609678826e-07,
          "best_u": -6.000000014401678,
          "best_v": -5.9999999855983255,
          "example_labels": "prefix_flag_17_24;struct_flag:full:prefix_17;struct_flag:prefix_24:prefix_17",
          "first_size": 17,
          "hessian_max_eigenvalue_at_equality": 8.881784197001252e-16,
          "hessian_min_eigenvalue_at_equality": -7.32971014492754,
          "local_hessian_nonpositive": true,
          "partition_count": 2,
          "profile": "0,0,0,0,0,0,0,0,0,0,0,0,0,0,0,0,0,0,0,0,0,0,0,0,0,0,0,0,0,0,0,0,0,0,0,0,0,0,0,0,0,0,0,0,0,0,0,0,0,0,0,0,0,0,0,0,0,0,0,0,0,0,0,0,0,0,0,0,0,0,0,0,6,0,0,0,0,0,0,0,0,0,0,0,82,0,0,0,0,0,0,0,0,0,0,0,390,0,0,0,0,0,0,0,0,0,0,0,810,0,0,0,0,0,0,0,0,0,0,0,810,0,0,0,0,0,0,0,0,0,0,0,390,0,0,0,0,0,0,0,0,0,0,0,82,0,0,0,0,0,0,0,0,0,0,0,6,0,0,0,0,0,0,0,0,0,0,0,0",
          "rest_size": 0,
          "second_size": 7,
          "shell": 12
        },
        {
          "best_F": 1.4210854715202004e-14,
          "best_gradient_norm": 6.726558050205023e-08,
          "best_u": -5.999999992849866,
          "best_v": -6.000000007150139,
          "example_labels": "prefix_flag_18_24;struct_flag:full:prefix_18;struct_flag:prefix_24:prefix_18;struct_symdiff:prefix_18:mog_row_3;struct_symdiff:prefix_18:w24_row_mask_3;swap:codeword_w24_split_by_mog_row_3;swap:struct_flag:full:mog_row_3;swap:struct_flag:full:w24_row_mask_3",
          "first_size": 18,
          "hessian_max_eigenvalue_at_equality": 8.881784197001252e-16,
          "hessian_min_eigenvalue_at_equality": -6.652173913043476,
          "local_hessian_nonpositive": true,
          "partition_count": 4,
          "profile": "0,0,0,0,0,0,0,0,0,0,0,0,0,0,0,0,0,0,0,0,0,0,0,0,0,0,0,0,0,0,0,0,0,0,0,0,0,0,0,0,0,0,0,0,0,0,0,0,0,0,0,0,0,0,0,0,0,0,0,0,0,0,0,0,0,0,0,0,0,0,0,0,0,0,0,0,0,0,0,0,0,0,0,0,18,0,0,0,0,0,0,0,0,0,0,0,180,0,0,0,0,0,0,0,0,0,0,0,630,0,0,0,0,0,0,0,0,0,0,0,920,0,0,0,0,0,0,0,0,0,0,0,630,0,0,0,0,0,0,0,0,0,0,0,180,0,0,0,0,0,0,0,0,0,0,0,18,0,0,0,0,0,0,0,0,0,0,0,0",
          "rest_size": 0,
          "second_size": 6,
          "shell": 12
        }
      ],
      "unique_profile_count": 3126,
      "unique_profile_count_by_shell": {
        "12": 1563,
        "16": 1563
      }
    },
    "witness": {
      "max_best_F": 1.4210854715202004e-14,
      "profile_csv": {
        "path": "data/invariants/d20/proof_obligations/d20_golay_shell_three_level_structured_probe/three_level_structured_profiles.csv",
        "sha256": "e4ae41353b378b41ce7e347b62ea10c2b5e8ae8de7f3010e3a9558741403b825"
      },
      "profile_csv_row_count": 3126,
      "tolerance": 1e-08,
      "top_profiles": [
        {
          "best_F": 1.4210854715202004e-14,
          "best_gradient_norm": 1.9777601356788236e-08,
          "best_u": -5.9999999901283205,
          "best_v": -6.000000009871675,
          "example_labels": "prefix_flag_1_24;struct_flag:full:prefix_1;struct_flag:prefix_24:prefix_1",
          "first_size": 1,
          "hessian_max_eigenvalue_at_equality": 0.0,
          "hessian_min_eigenvalue_at_equality": -1.4166666666666667,
          "local_hessian_nonpositive": true,
          "partition_count": 2,
          "profile": "0,0,0,0,0,0,0,0,0,0,0,0,1288,0,0,0,0,0,0,0,0,0,0,0,1288,0,0,0,0,0,0,0,0,0,0,0,0,0,0,0,0,0,0,0,0,0,0,0,0,0,0,0,0,0,0,0,0,0,0,0,0,0,0,0,0,0,0,0,0,0,0,0,0,0,0,0,0,0,0,0,0,0,0,0,0,0,0,0,0,0,0,0,0,0,0,0,0,0,0,0,0,0,0,0,0,0,0,0,0,0,0,0,0,0,0,0,0,0,0,0,0,0,0,0,0,0,0,0,0,0,0,0,0,0,0,0,0,0,0,0,0,0,0,0,0,0,0,0,0,0,0,0,0,0,0,0,0,0,0,0,0,0,0,0,0,0,0,0,0",
          "rest_size": 0,
          "second_size": 23,
          "shell": 12
        },
        {
          "best_F": 1.4210854715202004e-14,
          "best_gradient_norm": 2.9476039550728006e-08,
          "best_u": -5.999999992309375,
          "best_v": -6.0000000076906215,
          "example_labels": "prefix_flag_2_24;struct_flag:full:prefix_2;struct_flag:prefix_24:prefix_2",
          "first_size": 2,
          "hessian_max_eigenvalue_at_equality": -6.661338147750939e-16,
          "hessian_min_eigenvalue_at_equality": -2.7101449275362297,
          "local_hessian_nonpositive": true,
          "partition_count": 2,
          "profile": "0,0,0,0,0,0,0,0,0,0,0,0,616,0,0,0,0,0,0,0,0,0,0,0,1344,0,0,0,0,0,0,0,0,0,0,0,616,0,0,0,0,0,0,0,0,0,0,0,0,0,0,0,0,0,0,0,0,0,0,0,0,0,0,0,0,0,0,0,0,0,0,0,0,0,0,0,0,0,0,0,0,0,0,0,0,0,0,0,0,0,0,0,0,0,0,0,0,0,0,0,0,0,0,0,0,0,0,0,0,0,0,0,0,0,0,0,0,0,0,0,0,0,0,0,0,0,0,0,0,0,0,0,0,0,0,0,0,0,0,0,0,0,0,0,0,0,0,0,0,0,0,0,0,0,0,0,0,0,0,0,0,0,0,0,0,0,0,0,0",
          "rest_size": 0,
          "second_size": 22,
          "shell": 12
        },
        {
          "best_F": 1.4210854715202004e-14,
          "best_gradient_norm": 6.726558050205023e-08,
          "best_u": -6.000000007150139,
          "best_v": -5.999999992849866,
          "example_labels": "codeword_w24_split_by_mog_row_0;prefix_flag_6_24;struct_flag:full:mog_row_0;struct_flag:full:prefix_6;struct_flag:full:w24_row_mask_0;struct_flag:prefix_24:mog_row_0;struct_flag:prefix_24:prefix_6;struct_flag:prefix_24:w24_row_mask_0",
          "first_size": 6,
          "hessian_max_eigenvalue_at_equality": 8.881784197001252e-16,
          "hessian_min_eigenvalue_at_equality": -6.652173913043476,
          "local_hessian_nonpositive": true,
          "partition_count": 4,
          "profile": "0,0,0,0,0,0,0,0,0,0,0,0,18,0,0,0,0,0,0,0,0,0,0,0,180,0,0,0,0,0,0,0,0,0,0,0,630,0,0,0,0,0,0,0,0,0,0,0,920,0,0,0,0,0,0,0,0,0,0,0,630,0,0,0,0,0,0,0,0,0,0,0,180,0,0,0,0,0,0,0,0,0,0,0,18,0,0,0,0,0,0,0,0,0,0,0,0,0,0,0,0,0,0,0,0,0,0,0,0,0,0,0,0,0,0,0,0,0,0,0,0,0,0,0,0,0,0,0,0,0,0,0,0,0,0,0,0,0,0,0,0,0,0,0,0,0,0,0,0,0,0,0,0,0,0,0,0,0,0,0,0,0,0,0,0,0,0,0,0",
          "rest_size": 0,
          "second_size": 18,
          "shell": 12
        },
        {
          "best_F": 1.4210854715202004e-14,
          "best_gradient_norm": 1.4928454609678826e-07,
          "best_u": -5.9999999855983255,
          "best_v": -6.000000014401678,
          "example_labels": "prefix_flag_7_24;struct_flag:full:prefix_7;struct_flag:prefix_24:prefix_7",
          "first_size": 7,
          "hessian_max_eigenvalue_at_equality": -1.7763568394002505e-15,
          "hessian_min_eigenvalue_at_equality": -7.329710144927535,
          "local_hessian_nonpositive": true,
          "partition_count": 2,
          "profile": "0,0,0,0,0,0,0,0,0,0,0,0,6,0,0,0,0,0,0,0,0,0,0,0,82,0,0,0,0,0,0,0,0,0,0,0,390,0,0,0,0,0,0,0,0,0,0,0,810,0,0,0,0,0,0,0,0,0,0,0,810,0,0,0,0,0,0,0,0,0,0,0,390,0,0,0,0,0,0,0,0,0,0,0,82,0,0,0,0,0,0,0,0,0,0,0,6,0,0,0,0,0,0,0,0,0,0,0,0,0,0,0,0,0,0,0,0,0,0,0,0,0,0,0,0,0,0,0,0,0,0,0,0,0,0,0,0,0,0,0,0,0,0,0,0,0,0,0,0,0,0,0,0,0,0,0,0,0,0,0,0,0,0,0,0,0,0,0,0",
          "rest_size": 0,
          "second_size": 17,
          "shell": 12
        },
        {
          "best_F": 1.4210854715202004e-14,
          "best_gradient_norm": 2.0920576696649625e-07,
          "best_u": -6.000000017790371,
          "best_v": -5.9999999822096255,
          "example_labels": "prefix_flag_9_24;struct_flag:full:prefix_9;struct_flag:prefix_24:prefix_9",
          "first_size": 9,
          "hessian_max_eigenvalue_at_equality": 1.7763568394002505e-14,
          "hessian_min_eigenvalue_at_equality": -8.315217391304355,
          "local_hessian_nonpositive": true,
          "partition_count": 2,
          "profile": "0,0,0,0,0,0,0,0,0,0,0,0,1,0,0,0,0,0,0,0,0,0,0,0,9,0,0,0,0,0,0,0,0,0,0,0,108,0,0,0,0,0,0,0,0,0,0,0,396,0,0,0,0,0,0,0,0,0,0,0,774,0,0,0,0,0,0,0,0,0,0,0,774,0,0,0,0,0,0,0,0,0,0,0,396,0,0,0,0,0,0,0,0,0,0,0,108,0,0,0,0,0,0,0,0,0,0,0,9,0,0,0,0,0,0,0,0,0,0,0,1,0,0,0,0,0,0,0,0,0,0,0,0,0,0,0,0,0,0,0,0,0,0,0,0,0,0,0,0,0,0,0,0,0,0,0,0,0,0,0,0,0,0,0,0,0,0,0,0",
          "rest_size": 0,
          "second_size": 15,
          "shell": 12
        },
        {
          "best_F": 1.4210854715202004e-14,
          "best_gradient_norm": 3.378995101081575e-08,
          "best_u": -5.999999997229201,
          "best_v": -6.000000002770795,
          "example_labels": "prefix_flag_10_24;struct_flag:full:prefix_10;struct_flag:prefix_24:prefix_10",
          "first_size": 10,
          "hessian_max_eigenvalue_at_equality": 0.0,
          "hessian_min_eigenvalue_at_equality": -8.623188405797103,
          "local_hessian_nonpositive": true,
          "partition_count": 2,
          "profile": "0,0,0,0,0,0,0,0,0,0,0,0,1,0,0,0,0,0,0,0,0,0,0,0,0,0,0,0,0,0,0,0,0,0,0,0,45,0,0,0,0,0,0,0,0,0,0,0,240,0,0,0,0,0,0,0,0,0,0,0,570,0,0,0,0,0,0,0,0,0,0,0,864,0,0,0,0,0,0,0,0,0,0,0,570,0,0,0,0,0,0,0,0,0,0,0,240,0,0,0,0,0,0,0,0,0,0,0,45,0,0,0,0,0,0,0,0,0,0,0,0,0,0,0,0,0,0,0,0,0,0,0,1,0,0,0,0,0,0,0,0,0,0,0,0,0,0,0,0,0,0,0,0,0,0,0,0,0,0,0,0,0,0,0,0,0,0,0,0",
          "rest_size": 0,
          "second_size": 14,
          "shell": 12
        },
        {
          "best_F": 1.4210854715202004e-14,
          "best_gradient_norm": 1.9398959963375935e-07,
          "best_u": -5.99999998442645,
          "best_v": -6.000000015573547,
          "example_labels": "prefix_flag_11_24;struct_flag:full:prefix_11;struct_flag:prefix_24:prefix_11",
          "first_size": 11,
          "hessian_max_eigenvalue_at_equality": 5.329070518200751e-15,
          "hessian_min_eigenvalue_at_equality": -8.807971014492754,
          "local_hessian_nonpositive": true,
          "partition_count": 2,
          "profile": "0,0,0,0,0,0,0,0,0,0,0,0,1,0,0,0,0,0,0,0,0,0,0,0,0,0,0,0,0,0,0,0,0,0,0,0,0,0,0,0,0,0,0,0,0,0,0,0,165,0,0,0,0,0,0,0,0,0,0,0,330,0,0,0,0,0,0,0,0,0,0,0,792,0,0,0,0,0,0,0,0,0,0,0,792,0,0,0,0,0,0,0,0,0,0,0,330,0,0,0,0,0,0,0,0,0,0,0,165,0,0,0,0,0,0,0,0,0,0,0,0,0,0,0,0,0,0,0,0,0,0,0,0,0,0,0,0,0,0,0,0,0,0,0,1,0,0,0,0,0,0,0,0,0,0,0,0,0,0,0,0,0,0,0,0,0,0,0,0",
          "rest_size": 0,
          "second_size": 13,
          "shell": 12
        },
        {
          "best_F": 1.4210854715202004e-14,
          "best_gradient_norm": 1.9398959963375935e-07,
          "best_u": -6.000000015573547,
          "best_v": -5.99999998442645,
          "example_labels": "prefix_flag_13_24;struct_flag:full:prefix_13;struct_flag:prefix_24:prefix_13",
          "first_size": 13,
          "hessian_max_eigenvalue_at_equality": 5.329070518200751e-15,
          "hessian_min_eigenvalue_at_equality": -8.807971014492754,
          "local_hessian_nonpositive": true,
          "partition_count": 2,
          "profile": "0,0,0,0,0,0,0,0,0,0,0,0,0,0,0,0,0,0,0,0,0,0,0,0,1,0,0,0,0,0,0,0,0,0,0,0,0,0,0,0,0,0,0,0,0,0,0,0,0,0,0,0,0,0,0,0,0,0,0,0,165,0,0,0,0,0,0,0,0,0,0,0,330,0,0,0,0,0,0,0,0,0,0,0,792,0,0,0,0,0,0,0,0,0,0,0,792,0,0,0,0,0,0,0,0,0,0,0,330,0,0,0,0,0,0,0,0,0,0,0,165,0,0,0,0,0,0,0,0,0,0,0,0,0,0,0,0,0,0,0,0,0,0,0,0,0,0,0,0,0,0,0,0,0,0,0,1,0,0,0,0,0,0,0,0,0,0,0,0",
          "rest_size": 0,
          "second_size": 11,
          "shell": 12
        },
        {
          "best_F": 1.4210854715202004e-14,
          "best_gradient_norm": 3.378995101081575e-08,
          "best_u": -6.000000002770795,
          "best_v": -5.999999997229201,
          "example_labels": "prefix_flag_14_24;struct_flag:full:prefix_14;struct_flag:prefix_24:prefix_14",
          "first_size": 14,
          "hessian_max_eigenvalue_at_equality": -5.329070518200751e-15,
          "hessian_min_eigenvalue_at_equality": -8.623188405797094,
          "local_hessian_nonpositive": true,
          "partition_count": 2,
          "profile": "0,0,0,0,0,0,0,0,0,0,0,0,0,0,0,0,0,0,0,0,0,0,0,0,0,0,0,0,0,0,0,0,0,0,0,0,1,0,0,0,0,0,0,0,0,0,0,0,0,0,0,0,0,0,0,0,0,0,0,0,45,0,0,0,0,0,0,0,0,0,0,0,240,0,0,0,0,0,0,0,0,0,0,0,570,0,0,0,0,0,0,0,0,0,0,0,864,0,0,0,0,0,0,0,0,0,0,0,570,0,0,0,0,0,0,0,0,0,0,0,240,0,0,0,0,0,0,0,0,0,0,0,45,0,0,0,0,0,0,0,0,0,0,0,0,0,0,0,0,0,0,0,0,0,0,0,1,0,0,0,0,0,0,0,0,0,0,0,0",
          "rest_size": 0,
          "second_size": 10,
          "shell": 12
        },
        {
          "best_F": 1.4210854715202004e-14,
          "best_gradient_norm": 2.0920576696649625e-07,
          "best_u": -5.9999999822096255,
          "best_v": -6.000000017790371,
          "example_labels": "prefix_flag_15_24;struct_flag:full:prefix_15;struct_flag:prefix_24:prefix_15",
          "first_size": 15,
          "hessian_max_eigenvalue_at_equality": 8.881784197001252e-15,
          "hessian_min_eigenvalue_at_equality": -8.31521739130435,
          "local_hessian_nonpositive": true,
          "partition_count": 2,
          "profile": "0,0,0,0,0,0,0,0,0,0,0,0,0,0,0,0,0,0,0,0,0,0,0,0,0,0,0,0,0,0,0,0,0,0,0,0,0,0,0,0,0,0,0,0,0,0,0,0,1,0,0,0,0,0,0,0,0,0,0,0,9,0,0,0,0,0,0,0,0,0,0,0,108,0,0,0,0,0,0,0,0,0,0,0,396,0,0,0,0,0,0,0,0,0,0,0,774,0,0,0,0,0,0,0,0,0,0,0,774,0,0,0,0,0,0,0,0,0,0,0,396,0,0,0,0,0,0,0,0,0,0,0,108,0,0,0,0,0,0,0,0,0,0,0,9,0,0,0,0,0,0,0,0,0,0,0,1,0,0,0,0,0,0,0,0,0,0,0,0",
          "rest_size": 0,
          "second_size": 9,
          "shell": 12
        },
        {
          "best_F": 1.4210854715202004e-14,
          "best_gradient_norm": 1.4928454609678826e-07,
          "best_u": -6.000000014401678,
          "best_v": -5.9999999855983255,
          "example_labels": "prefix_flag_17_24;struct_flag:full:prefix_17;struct_flag:prefix_24:prefix_17",
          "first_size": 17,
          "hessian_max_eigenvalue_at_equality": 8.881784197001252e-16,
          "hessian_min_eigenvalue_at_equality": -7.32971014492754,
          "local_hessian_nonpositive": true,
          "partition_count": 2,
          "profile": "0,0,0,0,0,0,0,0,0,0,0,0,0,0,0,0,0,0,0,0,0,0,0,0,0,0,0,0,0,0,0,0,0,0,0,0,0,0,0,0,0,0,0,0,0,0,0,0,0,0,0,0,0,0,0,0,0,0,0,0,0,0,0,0,0,0,0,0,0,0,0,0,6,0,0,0,0,0,0,0,0,0,0,0,82,0,0,0,0,0,0,0,0,0,0,0,390,0,0,0,0,0,0,0,0,0,0,0,810,0,0,0,0,0,0,0,0,0,0,0,810,0,0,0,0,0,0,0,0,0,0,0,390,0,0,0,0,0,0,0,0,0,0,0,82,0,0,0,0,0,0,0,0,0,0,0,6,0,0,0,0,0,0,0,0,0,0,0,0",
          "rest_size": 0,
          "second_size": 7,
          "shell": 12
        },
        {
          "best_F": 1.4210854715202004e-14,
          "best_gradient_norm": 6.726558050205023e-08,
          "best_u": -5.999999992849866,
          "best_v": -6.000000007150139,
          "example_labels": "prefix_flag_18_24;struct_flag:full:prefix_18;struct_flag:prefix_24:prefix_18;struct_symdiff:prefix_18:mog_row_3;struct_symdiff:prefix_18:w24_row_mask_3;swap:codeword_w24_split_by_mog_row_3;swap:struct_flag:full:mog_row_3;swap:struct_flag:full:w24_row_mask_3",
          "first_size": 18,
          "hessian_max_eigenvalue_at_equality": 8.881784197001252e-16,
          "hessian_min_eigenvalue_at_equality": -6.652173913043476,
          "local_hessian_nonpositive": true,
          "partition_count": 4,
          "profile": "0,0,0,0,0,0,0,0,0,0,0,0,0,0,0,0,0,0,0,0,0,0,0,0,0,0,0,0,0,0,0,0,0,0,0,0,0,0,0,0,0,0,0,0,0,0,0,0,0,0,0,0,0,0,0,0,0,0,0,0,0,0,0,0,0,0,0,0,0,0,0,0,0,0,0,0,0,0,0,0,0,0,0,0,18,0,0,0,0,0,0,0,0,0,0,0,180,0,0,0,0,0,0,0,0,0,0,0,630,0,0,0,0,0,0,0,0,0,0,0,920,0,0,0,0,0,0,0,0,0,0,0,630,0,0,0,0,0,0,0,0,0,0,0,180,0,0,0,0,0,0,0,0,0,0,0,18,0,0,0,0,0,0,0,0,0,0,0,0",
          "rest_size": 0,
          "second_size": 6,
          "shell": 12
        }
      ]
    }
  }
}
