{
  "certified_reading": [
    "the dominant repaired recurrent class supports a reversible native-biased transfer operator",
    "the stationary distribution is exactly reproducible from weighted degrees",
    "the spectral bottleneck carries small but nonzero derived flux",
    "the flow center sits near the disk core and is pulled toward the right boundary side"
  ],
  "checks": {
    "boundary_masses_are_expected": true,
    "center_table_shape_matches_codebook": true,
    "edge_flux_sums_to_one": true,
    "edge_table_shape_matches_codebook": true,
    "flow_center_is_away_from_cut_center": true,
    "flow_center_is_closer_to_right_than_gate": true,
    "flow_center_is_inside_disk": true,
    "observable_table_shape_matches_codebook": true,
    "repaired_automaton_certificate_certified": true,
    "repaired_automaton_report_certified": true,
    "side_masses_are_expected": true,
    "side_table_shape_matches_codebook": true,
    "spectral_cut_flux_is_expected": true,
    "state_table_shape_matches_codebook": true,
    "stationary_mass_sums_to_one": true,
    "transfer_counts_are_expected": true,
    "transition_weight_profile_is_expected": true
  },
  "schema": "c985.d20_signature_boundary_spine_aperture_closure_tail_transfer_operator_certificate@1",
  "status": "C985_D20_SIGNATURE_BOUNDARY_SPINE_APERTURE_CLOSURE_TAIL_TRANSFER_OPERATOR_CERTIFIED",
  "witness": {
    "boundary_masses": {
      "gate_mass_x1e12": 770943978,
      "gate_state_id": 811,
      "left_mass_x1e12": 2141511051,
      "left_state_id": 332,
      "right_mass_x1e12": 1627548398,
      "right_state_id": 626
    },
    "center_table_sha256": "af66e00121a1ca531f6572634f7e2e1e5ada4631c6e6d25e220e02122f6b967e",
    "cut_center": {
      "center_code": 2,
      "center_id": 3,
      "center_radius_x1e12": 121020638000,
      "center_x_x1e12": -4400616000,
      "center_y_x1e12": 120940603250,
      "distance_to_cut_center_x1e12": 0,
      "distance_to_flow_center_x1e12": 294814140000,
      "distance_to_gate_x1e12": 119429420000,
      "distance_to_left_boundary_x1e12": 219007807000,
      "distance_to_right_boundary_x1e12": 270334365000,
      "support_mass_x1e12": 0,
      "support_state_count": 0
    },
    "edge_profile": {
      "derived_edge_count": 833,
      "derived_edge_weight": 833,
      "derived_only_edge_count": 746,
      "native_edge_count": 1668,
      "native_edge_weight": 5004
    },
    "edge_table_sha256": "d0ef2fdc81f28fbaa40c3c7ae2b0480ad73c391b2a7a770f070a6c7e3789df34",
    "mass_center": {
      "center_code": 0,
      "center_id": 0,
      "center_radius_x1e12": 49389559000,
      "center_x_x1e12": 46510986546,
      "center_y_x1e12": -16614954352,
      "distance_to_cut_center_x1e12": 294814140000,
      "distance_to_flow_center_x1e12": 0,
      "distance_to_gate_x1e12": 192310698000,
      "distance_to_left_boundary_x1e12": 132863678000,
      "distance_to_right_boundary_x1e12": 41209484000,
      "support_mass_x1e12": 1000000000000,
      "support_state_count": 787
    },
    "observable_table_sha256": "7ec493cb38c1cc71ab6a7d6263ffbfa8e7fd696aa479d272505ec1e7093462e4",
    "side_masses": {
      "-1": 115127634054,
      "1": 884872365946
    },
    "side_table_sha256": "b37f775d8ff866b85fb3b3696f4eb79a75cbcc0c9a4e94d1d2c178ccc61b2740",
    "spectral_cut_flow": {
      "cut_edge_count": 6,
      "cut_flux_x1e12": 1027925304,
      "cut_weight": 6,
      "weighted_cut_conductance_x1e12": 4464286000
    },
    "state_table_sha256": "29c5e5771aa2ef7afc39f300c80fcd55cf3cd8776311fef6971636fc095b8122",
    "top_stationary_mass_x1e12": 7623779339,
    "top_stationary_state_id": 443,
    "total_edge_weight": 5837,
    "total_weighted_degree": 11674,
    "transfer_edge_count": 2501,
    "transfer_state_count": 787,
    "weight_rule": {
      "derived_edge_weight": 1,
      "native_edge_weight": 3
    }
  }
}
