{
  "all_checks_pass": true,
  "certificate_sha256": "b9a0f2606849d763aa47d3e8a1da2d2bb9d831d2c6a7b98477cbb6113c5ecee5",
  "checks": {
    "all_generator_commutators_vanish": true,
    "all_generators_are_involutions": true,
    "all_generators_preserve_kernel_parity": true,
    "all_internal_generator_sector26_clock_shifts_are_even": true,
    "all_operator_basis_masks_satisfy_kernel_parity": true,
    "crossing_primitive_generators_are_excluded_but_pair_closed": true,
    "finite_kernel_candidate_is_certified": true,
    "fourier_mode_classifier_is_certified": true,
    "full_operator_basis_has_even_sector26_clock_only": true,
    "generator_count_is_8_primitive_plus_3_composite": true,
    "generator_masks_have_rank10_with_one_relation": true,
    "multiplication_table_is_closed_on_operator_basis": true,
    "operator_basis_has_1024_rank10_masks": true,
    "paired_cross_return_clock_shifts_are_2_8_2": true,
    "primitive_preserving_clock_shifts_match_basis_clock": true,
    "sector26_clock_defect_is_classified_on_generator_products": true,
    "sector26_clock_defect_is_only_overlap_cancellation": true,
    "sector26_clock_defect_vanishes_on_disjoint_source_products": true
  },
  "claim": "The rank-10 finite string-kernel candidate carries a certified finite generator algebra. At the translation-generator layer this algebra is the abelian exponent-2 operator group C2^10 generated by eight primitive-preserving moves and three paired cross-return composites. The 11 named generators have one nontrivial dependency, C5_9 C5_10 C9_10 = 1, and every internal generator has an even sector-26 clock shift. The sector-26 clock is not a group homomorphism on this exponent-2 layer; its finite overlap-cancellation defect is explicitly classified.",
  "definition": {
    "commutator_test": "For translation operators T_a and T_b, the commutator is T_a T_b T_a T_b = T_0.",
    "finite_generator_algebra": "The translation operator algebra generated by the primitive-preserving masks and paired cross-return composite masks under xor multiplication.",
    "operator_basis": "The 1024 translations by masks in the rank-10 kernel hyperplane m_5 + m_9 + m_10 = 0.",
    "sector26_clock_test": "The sector-26 clock is checked against generator products. Defects occur exactly when source generator supports overlap and cancel under xor."
  },
  "derived": {
    "algebra_summary": {
      "algebra_group_type": "C2^10 translation operator group",
      "all_commutators_zero": true,
      "corrected_hidden_clock_shift_histogram_on_named_generators": {
        "0": 4,
        "13": 7
      },
      "named_generator_count": 11,
      "named_generator_rank": 10,
      "operator_basis_count": 1024,
      "operator_basis_rank": 10,
      "paired_cross_return_generator_count": 3,
      "primitive_preserving_generator_count": 8,
      "relation_count_mod_involutions": 1,
      "sector26_clock_defect_histogram_on_generator_products": {
        "0": 104,
        "10": 2,
        "16": 2,
        "18": 4,
        "2": 1,
        "22": 2,
        "24": 2,
        "4": 3,
        "6": 1
      },
      "sector26_clock_defect_row_count": 17,
      "sector26_clock_histogram_on_operator_basis": {
        "0": 83,
        "10": 77,
        "12": 79,
        "14": 78,
        "16": 82,
        "18": 82,
        "2": 77,
        "20": 75,
        "22": 73,
        "24": 82,
        "4": 78,
        "6": 80,
        "8": 78
      },
      "sector26_clock_shift_histogram_on_named_generators": {
        "10": 1,
        "12": 1,
        "14": 2,
        "18": 2,
        "2": 2,
        "24": 1,
        "8": 2
      }
    },
    "commutator_table": [
      {
        "commutator_mask": 0,
        "left": "P0",
        "right": "P0"
      },
      {
        "commutator_mask": 0,
        "left": "P0",
        "right": "P1"
      },
      {
        "commutator_mask": 0,
        "left": "P0",
        "right": "P2"
      },
      {
        "commutator_mask": 0,
        "left": "P0",
        "right": "P3"
      },
      {
        "commutator_mask": 0,
        "left": "P0",
        "right": "P4"
      },
      {
        "commutator_mask": 0,
        "left": "P0",
        "right": "P6"
      },
      {
        "commutator_mask": 0,
        "left": "P0",
        "right": "P7"
      },
      {
        "commutator_mask": 0,
        "left": "P0",
        "right": "P8"
      },
      {
        "commutator_mask": 0,
        "left": "P0",
        "right": "C5_9"
      },
      {
        "commutator_mask": 0,
        "left": "P0",
        "right": "C5_10"
      },
      {
        "commutator_mask": 0,
        "left": "P0",
        "right": "C9_10"
      },
      {
        "commutator_mask": 0,
        "left": "P1",
        "right": "P0"
      },
      {
        "commutator_mask": 0,
        "left": "P1",
        "right": "P1"
      },
      {
        "commutator_mask": 0,
        "left": "P1",
        "right": "P2"
      },
      {
        "commutator_mask": 0,
        "left": "P1",
        "right": "P3"
      },
      {
        "commutator_mask": 0,
        "left": "P1",
        "right": "P4"
      },
      {
        "commutator_mask": 0,
        "left": "P1",
        "right": "P6"
      },
      {
        "commutator_mask": 0,
        "left": "P1",
        "right": "P7"
      },
      {
        "commutator_mask": 0,
        "left": "P1",
        "right": "P8"
      },
      {
        "commutator_mask": 0,
        "left": "P1",
        "right": "C5_9"
      },
      {
        "commutator_mask": 0,
        "left": "P1",
        "right": "C5_10"
      },
      {
        "commutator_mask": 0,
        "left": "P1",
        "right": "C9_10"
      },
      {
        "commutator_mask": 0,
        "left": "P2",
        "right": "P0"
      },
      {
        "commutator_mask": 0,
        "left": "P2",
        "right": "P1"
      },
      {
        "commutator_mask": 0,
        "left": "P2",
        "right": "P2"
      },
      {
        "commutator_mask": 0,
        "left": "P2",
        "right": "P3"
      },
      {
        "commutator_mask": 0,
        "left": "P2",
        "right": "P4"
      },
      {
        "commutator_mask": 0,
        "left": "P2",
        "right": "P6"
      },
      {
        "commutator_mask": 0,
        "left": "P2",
        "right": "P7"
      },
      {
        "commutator_mask": 0,
        "left": "P2",
        "right": "P8"
      },
      {
        "commutator_mask": 0,
        "left": "P2",
        "right": "C5_9"
      },
      {
        "commutator_mask": 0,
        "left": "P2",
        "right": "C5_10"
      },
      {
        "commutator_mask": 0,
        "left": "P2",
        "right": "C9_10"
      },
      {
        "commutator_mask": 0,
        "left": "P3",
        "right": "P0"
      },
      {
        "commutator_mask": 0,
        "left": "P3",
        "right": "P1"
      },
      {
        "commutator_mask": 0,
        "left": "P3",
        "right": "P2"
      },
      {
        "commutator_mask": 0,
        "left": "P3",
        "right": "P3"
      },
      {
        "commutator_mask": 0,
        "left": "P3",
        "right": "P4"
      },
      {
        "commutator_mask": 0,
        "left": "P3",
        "right": "P6"
      },
      {
        "commutator_mask": 0,
        "left": "P3",
        "right": "P7"
      },
      {
        "commutator_mask": 0,
        "left": "P3",
        "right": "P8"
      },
      {
        "commutator_mask": 0,
        "left": "P3",
        "right": "C5_9"
      },
      {
        "commutator_mask": 0,
        "left": "P3",
        "right": "C5_10"
      },
      {
        "commutator_mask": 0,
        "left": "P3",
        "right": "C9_10"
      },
      {
        "commutator_mask": 0,
        "left": "P4",
        "right": "P0"
      },
      {
        "commutator_mask": 0,
        "left": "P4",
        "right": "P1"
      },
      {
        "commutator_mask": 0,
        "left": "P4",
        "right": "P2"
      },
      {
        "commutator_mask": 0,
        "left": "P4",
        "right": "P3"
      },
      {
        "commutator_mask": 0,
        "left": "P4",
        "right": "P4"
      },
      {
        "commutator_mask": 0,
        "left": "P4",
        "right": "P6"
      },
      {
        "commutator_mask": 0,
        "left": "P4",
        "right": "P7"
      },
      {
        "commutator_mask": 0,
        "left": "P4",
        "right": "P8"
      },
      {
        "commutator_mask": 0,
        "left": "P4",
        "right": "C5_9"
      },
      {
        "commutator_mask": 0,
        "left": "P4",
        "right": "C5_10"
      },
      {
        "commutator_mask": 0,
        "left": "P4",
        "right": "C9_10"
      },
      {
        "commutator_mask": 0,
        "left": "P6",
        "right": "P0"
      },
      {
        "commutator_mask": 0,
        "left": "P6",
        "right": "P1"
      },
      {
        "commutator_mask": 0,
        "left": "P6",
        "right": "P2"
      },
      {
        "commutator_mask": 0,
        "left": "P6",
        "right": "P3"
      },
      {
        "commutator_mask": 0,
        "left": "P6",
        "right": "P4"
      },
      {
        "commutator_mask": 0,
        "left": "P6",
        "right": "P6"
      },
      {
        "commutator_mask": 0,
        "left": "P6",
        "right": "P7"
      },
      {
        "commutator_mask": 0,
        "left": "P6",
        "right": "P8"
      },
      {
        "commutator_mask": 0,
        "left": "P6",
        "right": "C5_9"
      },
      {
        "commutator_mask": 0,
        "left": "P6",
        "right": "C5_10"
      },
      {
        "commutator_mask": 0,
        "left": "P6",
        "right": "C9_10"
      },
      {
        "commutator_mask": 0,
        "left": "P7",
        "right": "P0"
      },
      {
        "commutator_mask": 0,
        "left": "P7",
        "right": "P1"
      },
      {
        "commutator_mask": 0,
        "left": "P7",
        "right": "P2"
      },
      {
        "commutator_mask": 0,
        "left": "P7",
        "right": "P3"
      },
      {
        "commutator_mask": 0,
        "left": "P7",
        "right": "P4"
      },
      {
        "commutator_mask": 0,
        "left": "P7",
        "right": "P6"
      },
      {
        "commutator_mask": 0,
        "left": "P7",
        "right": "P7"
      },
      {
        "commutator_mask": 0,
        "left": "P7",
        "right": "P8"
      },
      {
        "commutator_mask": 0,
        "left": "P7",
        "right": "C5_9"
      },
      {
        "commutator_mask": 0,
        "left": "P7",
        "right": "C5_10"
      },
      {
        "commutator_mask": 0,
        "left": "P7",
        "right": "C9_10"
      },
      {
        "commutator_mask": 0,
        "left": "P8",
        "right": "P0"
      },
      {
        "commutator_mask": 0,
        "left": "P8",
        "right": "P1"
      },
      {
        "commutator_mask": 0,
        "left": "P8",
        "right": "P2"
      },
      {
        "commutator_mask": 0,
        "left": "P8",
        "right": "P3"
      },
      {
        "commutator_mask": 0,
        "left": "P8",
        "right": "P4"
      },
      {
        "commutator_mask": 0,
        "left": "P8",
        "right": "P6"
      },
      {
        "commutator_mask": 0,
        "left": "P8",
        "right": "P7"
      },
      {
        "commutator_mask": 0,
        "left": "P8",
        "right": "P8"
      },
      {
        "commutator_mask": 0,
        "left": "P8",
        "right": "C5_9"
      },
      {
        "commutator_mask": 0,
        "left": "P8",
        "right": "C5_10"
      },
      {
        "commutator_mask": 0,
        "left": "P8",
        "right": "C9_10"
      },
      {
        "commutator_mask": 0,
        "left": "C5_9",
        "right": "P0"
      },
      {
        "commutator_mask": 0,
        "left": "C5_9",
        "right": "P1"
      },
      {
        "commutator_mask": 0,
        "left": "C5_9",
        "right": "P2"
      },
      {
        "commutator_mask": 0,
        "left": "C5_9",
        "right": "P3"
      },
      {
        "commutator_mask": 0,
        "left": "C5_9",
        "right": "P4"
      },
      {
        "commutator_mask": 0,
        "left": "C5_9",
        "right": "P6"
      },
      {
        "commutator_mask": 0,
        "left": "C5_9",
        "right": "P7"
      },
      {
        "commutator_mask": 0,
        "left": "C5_9",
        "right": "P8"
      },
      {
        "commutator_mask": 0,
        "left": "C5_9",
        "right": "C5_9"
      },
      {
        "commutator_mask": 0,
        "left": "C5_9",
        "right": "C5_10"
      },
      {
        "commutator_mask": 0,
        "left": "C5_9",
        "right": "C9_10"
      },
      {
        "commutator_mask": 0,
        "left": "C5_10",
        "right": "P0"
      },
      {
        "commutator_mask": 0,
        "left": "C5_10",
        "right": "P1"
      },
      {
        "commutator_mask": 0,
        "left": "C5_10",
        "right": "P2"
      },
      {
        "commutator_mask": 0,
        "left": "C5_10",
        "right": "P3"
      },
      {
        "commutator_mask": 0,
        "left": "C5_10",
        "right": "P4"
      },
      {
        "commutator_mask": 0,
        "left": "C5_10",
        "right": "P6"
      },
      {
        "commutator_mask": 0,
        "left": "C5_10",
        "right": "P7"
      },
      {
        "commutator_mask": 0,
        "left": "C5_10",
        "right": "P8"
      },
      {
        "commutator_mask": 0,
        "left": "C5_10",
        "right": "C5_9"
      },
      {
        "commutator_mask": 0,
        "left": "C5_10",
        "right": "C5_10"
      },
      {
        "commutator_mask": 0,
        "left": "C5_10",
        "right": "C9_10"
      },
      {
        "commutator_mask": 0,
        "left": "C9_10",
        "right": "P0"
      },
      {
        "commutator_mask": 0,
        "left": "C9_10",
        "right": "P1"
      },
      {
        "commutator_mask": 0,
        "left": "C9_10",
        "right": "P2"
      },
      {
        "commutator_mask": 0,
        "left": "C9_10",
        "right": "P3"
      },
      {
        "commutator_mask": 0,
        "left": "C9_10",
        "right": "P4"
      },
      {
        "commutator_mask": 0,
        "left": "C9_10",
        "right": "P6"
      },
      {
        "commutator_mask": 0,
        "left": "C9_10",
        "right": "P7"
      },
      {
        "commutator_mask": 0,
        "left": "C9_10",
        "right": "P8"
      },
      {
        "commutator_mask": 0,
        "left": "C9_10",
        "right": "C5_9"
      },
      {
        "commutator_mask": 0,
        "left": "C9_10",
        "right": "C5_10"
      },
      {
        "commutator_mask": 0,
        "left": "C9_10",
        "right": "C9_10"
      }
    ],
    "commutator_table_sha256": "8c5e879d04b1fcd464dfd3166ccef87e42aeb28e2b1381c8899d6e2344812585",
    "defining_relations": {
      "commutators": "[G_i, G_j] = 1 for all named generators at the translation layer",
      "dependency_relations": [
        {
          "product_mask": 0,
          "relation_labels": [
            "C5_9",
            "C5_10",
            "C9_10"
          ],
          "relation_size": 3,
          "relation_support_indices": [
            8,
            9,
            10
          ]
        }
      ],
      "involutions": [
        "P0^2 = 1",
        "P1^2 = 1",
        "P2^2 = 1",
        "P3^2 = 1",
        "P4^2 = 1",
        "P6^2 = 1",
        "P7^2 = 1",
        "P8^2 = 1",
        "C5_9^2 = 1",
        "C5_10^2 = 1",
        "C9_10^2 = 1"
      ],
      "operator_basis_masks_sha256": "4f4996e9a394fc2696fab155520527d24c48be6781ad3033c7dce9e537063dae",
      "operator_basis_multiplication_digest_sha256": "103ca5eb08eed4ec29c44e509b9de01c5e9e6b09e427af114e599341e881dffa"
    },
    "generator_multiplication_table": [
      {
        "clock_defect_mod26": 2,
        "left": "P0",
        "left_source_generators": [
          0
        ],
        "naive_clock_sum_mod26": 24,
        "product_is_identity": true,
        "product_mask": 0,
        "product_named_generator": null,
        "product_sector26_clock_shift_mod26": 0,
        "product_support_generator_ids": [],
        "right": "P0",
        "right_source_generators": [
          0
        ],
        "shared_source_generators": [
          0
        ]
      },
      {
        "clock_defect_mod26": 0,
        "left": "P0",
        "left_source_generators": [
          0
        ],
        "naive_clock_sum_mod26": 0,
        "product_is_identity": false,
        "product_mask": 3,
        "product_named_generator": null,
        "product_sector26_clock_shift_mod26": 0,
        "product_support_generator_ids": [
          0,
          1
        ],
        "right": "P1",
        "right_source_generators": [
          1
        ],
        "shared_source_generators": []
      },
      {
        "clock_defect_mod26": 0,
        "left": "P0",
        "left_source_generators": [
          0
        ],
        "naive_clock_sum_mod26": 4,
        "product_is_identity": false,
        "product_mask": 5,
        "product_named_generator": null,
        "product_sector26_clock_shift_mod26": 4,
        "product_support_generator_ids": [
          0,
          2
        ],
        "right": "P2",
        "right_source_generators": [
          2
        ],
        "shared_source_generators": []
      },
      {
        "clock_defect_mod26": 0,
        "left": "P0",
        "left_source_generators": [
          0
        ],
        "naive_clock_sum_mod26": 10,
        "product_is_identity": false,
        "product_mask": 9,
        "product_named_generator": null,
        "product_sector26_clock_shift_mod26": 10,
        "product_support_generator_ids": [
          0,
          3
        ],
        "right": "P3",
        "right_source_generators": [
          3
        ],
        "shared_source_generators": []
      },
      {
        "clock_defect_mod26": 0,
        "left": "P0",
        "left_source_generators": [
          0
        ],
        "naive_clock_sum_mod26": 0,
        "product_is_identity": false,
        "product_mask": 17,
        "product_named_generator": null,
        "product_sector26_clock_shift_mod26": 0,
        "product_support_generator_ids": [
          0,
          4
        ],
        "right": "P4",
        "right_source_generators": [
          4
        ],
        "shared_source_generators": []
      },
      {
        "clock_defect_mod26": 0,
        "left": "P0",
        "left_source_generators": [
          0
        ],
        "naive_clock_sum_mod26": 20,
        "product_is_identity": false,
        "product_mask": 65,
        "product_named_generator": null,
        "product_sector26_clock_shift_mod26": 20,
        "product_support_generator_ids": [
          0,
          6
        ],
        "right": "P6",
        "right_source_generators": [
          6
        ],
        "shared_source_generators": []
      },
      {
        "clock_defect_mod26": 0,
        "left": "P0",
        "left_source_generators": [
          0
        ],
        "naive_clock_sum_mod26": 22,
        "product_is_identity": false,
        "product_mask": 129,
        "product_named_generator": null,
        "product_sector26_clock_shift_mod26": 22,
        "product_support_generator_ids": [
          0,
          7
        ],
        "right": "P7",
        "right_source_generators": [
          7
        ],
        "shared_source_generators": []
      },
      {
        "clock_defect_mod26": 0,
        "left": "P0",
        "left_source_generators": [
          0
        ],
        "naive_clock_sum_mod26": 4,
        "product_is_identity": false,
        "product_mask": 257,
        "product_named_generator": null,
        "product_sector26_clock_shift_mod26": 4,
        "product_support_generator_ids": [
          0,
          8
        ],
        "right": "P8",
        "right_source_generators": [
          8
        ],
        "shared_source_generators": []
      },
      {
        "clock_defect_mod26": 0,
        "left": "P0",
        "left_source_generators": [
          0
        ],
        "naive_clock_sum_mod26": 14,
        "product_is_identity": false,
        "product_mask": 545,
        "product_named_generator": null,
        "product_sector26_clock_shift_mod26": 14,
        "product_support_generator_ids": [
          0,
          5,
          9
        ],
        "right": "C5_9",
        "right_source_generators": [
          5,
          9
        ],
        "shared_source_generators": []
      },
      {
        "clock_defect_mod26": 0,
        "left": "P0",
        "left_source_generators": [
          0
        ],
        "naive_clock_sum_mod26": 20,
        "product_is_identity": false,
        "product_mask": 1057,
        "product_named_generator": null,
        "product_sector26_clock_shift_mod26": 20,
        "product_support_generator_ids": [
          0,
          5,
          10
        ],
        "right": "C5_10",
        "right_source_generators": [
          5,
          10
        ],
        "shared_source_generators": []
      },
      {
        "clock_defect_mod26": 0,
        "left": "P0",
        "left_source_generators": [
          0
        ],
        "naive_clock_sum_mod26": 14,
        "product_is_identity": false,
        "product_mask": 1537,
        "product_named_generator": null,
        "product_sector26_clock_shift_mod26": 14,
        "product_support_generator_ids": [
          0,
          9,
          10
        ],
        "right": "C9_10",
        "right_source_generators": [
          9,
          10
        ],
        "shared_source_generators": []
      },
      {
        "clock_defect_mod26": 0,
        "left": "P1",
        "left_source_generators": [
          1
        ],
        "naive_clock_sum_mod26": 0,
        "product_is_identity": false,
        "product_mask": 3,
        "product_named_generator": null,
        "product_sector26_clock_shift_mod26": 0,
        "product_support_generator_ids": [
          0,
          1
        ],
        "right": "P0",
        "right_source_generators": [
          0
        ],
        "shared_source_generators": []
      },
      {
        "clock_defect_mod26": 24,
        "left": "P1",
        "left_source_generators": [
          1
        ],
        "naive_clock_sum_mod26": 2,
        "product_is_identity": true,
        "product_mask": 0,
        "product_named_generator": null,
        "product_sector26_clock_shift_mod26": 0,
        "product_support_generator_ids": [],
        "right": "P1",
        "right_source_generators": [
          1
        ],
        "shared_source_generators": [
          1
        ]
      },
      {
        "clock_defect_mod26": 0,
        "left": "P1",
        "left_source_generators": [
          1
        ],
        "naive_clock_sum_mod26": 6,
        "product_is_identity": false,
        "product_mask": 6,
        "product_named_generator": null,
        "product_sector26_clock_shift_mod26": 6,
        "product_support_generator_ids": [
          1,
          2
        ],
        "right": "P2",
        "right_source_generators": [
          2
        ],
        "shared_source_generators": []
      },
      {
        "clock_defect_mod26": 0,
        "left": "P1",
        "left_source_generators": [
          1
        ],
        "naive_clock_sum_mod26": 12,
        "product_is_identity": false,
        "product_mask": 10,
        "product_named_generator": null,
        "product_sector26_clock_shift_mod26": 12,
        "product_support_generator_ids": [
          1,
          3
        ],
        "right": "P3",
        "right_source_generators": [
          3
        ],
        "shared_source_generators": []
      },
      {
        "clock_defect_mod26": 0,
        "left": "P1",
        "left_source_generators": [
          1
        ],
        "naive_clock_sum_mod26": 2,
        "product_is_identity": false,
        "product_mask": 18,
        "product_named_generator": null,
        "product_sector26_clock_shift_mod26": 2,
        "product_support_generator_ids": [
          1,
          4
        ],
        "right": "P4",
        "right_source_generators": [
          4
        ],
        "shared_source_generators": []
      },
      {
        "clock_defect_mod26": 0,
        "left": "P1",
        "left_source_generators": [
          1
        ],
        "naive_clock_sum_mod26": 22,
        "product_is_identity": false,
        "product_mask": 66,
        "product_named_generator": null,
        "product_sector26_clock_shift_mod26": 22,
        "product_support_generator_ids": [
          1,
          6
        ],
        "right": "P6",
        "right_source_generators": [
          6
        ],
        "shared_source_generators": []
      },
      {
        "clock_defect_mod26": 0,
        "left": "P1",
        "left_source_generators": [
          1
        ],
        "naive_clock_sum_mod26": 24,
        "product_is_identity": false,
        "product_mask": 130,
        "product_named_generator": null,
        "product_sector26_clock_shift_mod26": 24,
        "product_support_generator_ids": [
          1,
          7
        ],
        "right": "P7",
        "right_source_generators": [
          7
        ],
        "shared_source_generators": []
      },
      {
        "clock_defect_mod26": 0,
        "left": "P1",
        "left_source_generators": [
          1
        ],
        "naive_clock_sum_mod26": 6,
        "product_is_identity": false,
        "product_mask": 258,
        "product_named_generator": null,
        "product_sector26_clock_shift_mod26": 6,
        "product_support_generator_ids": [
          1,
          8
        ],
        "right": "P8",
        "right_source_generators": [
          8
        ],
        "shared_source_generators": []
      },
      {
        "clock_defect_mod26": 0,
        "left": "P1",
        "left_source_generators": [
          1
        ],
        "naive_clock_sum_mod26": 16,
        "product_is_identity": false,
        "product_mask": 546,
        "product_named_generator": null,
        "product_sector26_clock_shift_mod26": 16,
        "product_support_generator_ids": [
          1,
          5,
          9
        ],
        "right": "C5_9",
        "right_source_generators": [
          5,
          9
        ],
        "shared_source_generators": []
      },
      {
        "clock_defect_mod26": 0,
        "left": "P1",
        "left_source_generators": [
          1
        ],
        "naive_clock_sum_mod26": 22,
        "product_is_identity": false,
        "product_mask": 1058,
        "product_named_generator": null,
        "product_sector26_clock_shift_mod26": 22,
        "product_support_generator_ids": [
          1,
          5,
          10
        ],
        "right": "C5_10",
        "right_source_generators": [
          5,
          10
        ],
        "shared_source_generators": []
      },
      {
        "clock_defect_mod26": 0,
        "left": "P1",
        "left_source_generators": [
          1
        ],
        "naive_clock_sum_mod26": 16,
        "product_is_identity": false,
        "product_mask": 1538,
        "product_named_generator": null,
        "product_sector26_clock_shift_mod26": 16,
        "product_support_generator_ids": [
          1,
          9,
          10
        ],
        "right": "C9_10",
        "right_source_generators": [
          9,
          10
        ],
        "shared_source_generators": []
      },
      {
        "clock_defect_mod26": 0,
        "left": "P2",
        "left_source_generators": [
          2
        ],
        "naive_clock_sum_mod26": 4,
        "product_is_identity": false,
        "product_mask": 5,
        "product_named_generator": null,
        "product_sector26_clock_shift_mod26": 4,
        "product_support_generator_ids": [
          0,
          2
        ],
        "right": "P0",
        "right_source_generators": [
          0
        ],
        "shared_source_generators": []
      },
      {
        "clock_defect_mod26": 0,
        "left": "P2",
        "left_source_generators": [
          2
        ],
        "naive_clock_sum_mod26": 6,
        "product_is_identity": false,
        "product_mask": 6,
        "product_named_generator": null,
        "product_sector26_clock_shift_mod26": 6,
        "product_support_generator_ids": [
          1,
          2
        ],
        "right": "P1",
        "right_source_generators": [
          1
        ],
        "shared_source_generators": []
      },
      {
        "clock_defect_mod26": 16,
        "left": "P2",
        "left_source_generators": [
          2
        ],
        "naive_clock_sum_mod26": 10,
        "product_is_identity": true,
        "product_mask": 0,
        "product_named_generator": null,
        "product_sector26_clock_shift_mod26": 0,
        "product_support_generator_ids": [],
        "right": "P2",
        "right_source_generators": [
          2
        ],
        "shared_source_generators": [
          2
        ]
      },
      {
        "clock_defect_mod26": 0,
        "left": "P2",
        "left_source_generators": [
          2
        ],
        "naive_clock_sum_mod26": 16,
        "product_is_identity": false,
        "product_mask": 12,
        "product_named_generator": null,
        "product_sector26_clock_shift_mod26": 16,
        "product_support_generator_ids": [
          2,
          3
        ],
        "right": "P3",
        "right_source_generators": [
          3
        ],
        "shared_source_generators": []
      },
      {
        "clock_defect_mod26": 0,
        "left": "P2",
        "left_source_generators": [
          2
        ],
        "naive_clock_sum_mod26": 6,
        "product_is_identity": false,
        "product_mask": 20,
        "product_named_generator": null,
        "product_sector26_clock_shift_mod26": 6,
        "product_support_generator_ids": [
          2,
          4
        ],
        "right": "P4",
        "right_source_generators": [
          4
        ],
        "shared_source_generators": []
      },
      {
        "clock_defect_mod26": 0,
        "left": "P2",
        "left_source_generators": [
          2
        ],
        "naive_clock_sum_mod26": 0,
        "product_is_identity": false,
        "product_mask": 68,
        "product_named_generator": null,
        "product_sector26_clock_shift_mod26": 0,
        "product_support_generator_ids": [
          2,
          6
        ],
        "right": "P6",
        "right_source_generators": [
          6
        ],
        "shared_source_generators": []
      },
      {
        "clock_defect_mod26": 0,
        "left": "P2",
        "left_source_generators": [
          2
        ],
        "naive_clock_sum_mod26": 2,
        "product_is_identity": false,
        "product_mask": 132,
        "product_named_generator": null,
        "product_sector26_clock_shift_mod26": 2,
        "product_support_generator_ids": [
          2,
          7
        ],
        "right": "P7",
        "right_source_generators": [
          7
        ],
        "shared_source_generators": []
      },
      {
        "clock_defect_mod26": 0,
        "left": "P2",
        "left_source_generators": [
          2
        ],
        "naive_clock_sum_mod26": 10,
        "product_is_identity": false,
        "product_mask": 260,
        "product_named_generator": null,
        "product_sector26_clock_shift_mod26": 10,
        "product_support_generator_ids": [
          2,
          8
        ],
        "right": "P8",
        "right_source_generators": [
          8
        ],
        "shared_source_generators": []
      },
      {
        "clock_defect_mod26": 0,
        "left": "P2",
        "left_source_generators": [
          2
        ],
        "naive_clock_sum_mod26": 20,
        "product_is_identity": false,
        "product_mask": 548,
        "product_named_generator": null,
        "product_sector26_clock_shift_mod26": 20,
        "product_support_generator_ids": [
          2,
          5,
          9
        ],
        "right": "C5_9",
        "right_source_generators": [
          5,
          9
        ],
        "shared_source_generators": []
      },
      {
        "clock_defect_mod26": 0,
        "left": "P2",
        "left_source_generators": [
          2
        ],
        "naive_clock_sum_mod26": 0,
        "product_is_identity": false,
        "product_mask": 1060,
        "product_named_generator": null,
        "product_sector26_clock_shift_mod26": 0,
        "product_support_generator_ids": [
          2,
          5,
          10
        ],
        "right": "C5_10",
        "right_source_generators": [
          5,
          10
        ],
        "shared_source_generators": []
      },
      {
        "clock_defect_mod26": 0,
        "left": "P2",
        "left_source_generators": [
          2
        ],
        "naive_clock_sum_mod26": 20,
        "product_is_identity": false,
        "product_mask": 1540,
        "product_named_generator": null,
        "product_sector26_clock_shift_mod26": 20,
        "product_support_generator_ids": [
          2,
          9,
          10
        ],
        "right": "C9_10",
        "right_source_generators": [
          9,
          10
        ],
        "shared_source_generators": []
      },
      {
        "clock_defect_mod26": 0,
        "left": "P3",
        "left_source_generators": [
          3
        ],
        "naive_clock_sum_mod26": 10,
        "product_is_identity": false,
        "product_mask": 9,
        "product_named_generator": null,
        "product_sector26_clock_shift_mod26": 10,
        "product_support_generator_ids": [
          0,
          3
        ],
        "right": "P0",
        "right_source_generators": [
          0
        ],
        "shared_source_generators": []
      },
      {
        "clock_defect_mod26": 0,
        "left": "P3",
        "left_source_generators": [
          3
        ],
        "naive_clock_sum_mod26": 12,
        "product_is_identity": false,
        "product_mask": 10,
        "product_named_generator": null,
        "product_sector26_clock_shift_mod26": 12,
        "product_support_generator_ids": [
          1,
          3
        ],
        "right": "P1",
        "right_source_generators": [
          1
        ],
        "shared_source_generators": []
      },
      {
        "clock_defect_mod26": 0,
        "left": "P3",
        "left_source_generators": [
          3
        ],
        "naive_clock_sum_mod26": 16,
        "product_is_identity": false,
        "product_mask": 12,
        "product_named_generator": null,
        "product_sector26_clock_shift_mod26": 16,
        "product_support_generator_ids": [
          2,
          3
        ],
        "right": "P2",
        "right_source_generators": [
          2
        ],
        "shared_source_generators": []
      },
      {
        "clock_defect_mod26": 4,
        "left": "P3",
        "left_source_generators": [
          3
        ],
        "naive_clock_sum_mod26": 22,
        "product_is_identity": true,
        "product_mask": 0,
        "product_named_generator": null,
        "product_sector26_clock_shift_mod26": 0,
        "product_support_generator_ids": [],
        "right": "P3",
        "right_source_generators": [
          3
        ],
        "shared_source_generators": [
          3
        ]
      },
      {
        "clock_defect_mod26": 0,
        "left": "P3",
        "left_source_generators": [
          3
        ],
        "naive_clock_sum_mod26": 12,
        "product_is_identity": false,
        "product_mask": 24,
        "product_named_generator": null,
        "product_sector26_clock_shift_mod26": 12,
        "product_support_generator_ids": [
          3,
          4
        ],
        "right": "P4",
        "right_source_generators": [
          4
        ],
        "shared_source_generators": []
      },
      {
        "clock_defect_mod26": 0,
        "left": "P3",
        "left_source_generators": [
          3
        ],
        "naive_clock_sum_mod26": 6,
        "product_is_identity": false,
        "product_mask": 72,
        "product_named_generator": null,
        "product_sector26_clock_shift_mod26": 6,
        "product_support_generator_ids": [
          3,
          6
        ],
        "right": "P6",
        "right_source_generators": [
          6
        ],
        "shared_source_generators": []
      },
      {
        "clock_defect_mod26": 0,
        "left": "P3",
        "left_source_generators": [
          3
        ],
        "naive_clock_sum_mod26": 8,
        "product_is_identity": false,
        "product_mask": 136,
        "product_named_generator": null,
        "product_sector26_clock_shift_mod26": 8,
        "product_support_generator_ids": [
          3,
          7
        ],
        "right": "P7",
        "right_source_generators": [
          7
        ],
        "shared_source_generators": []
      },
      {
        "clock_defect_mod26": 0,
        "left": "P3",
        "left_source_generators": [
          3
        ],
        "naive_clock_sum_mod26": 16,
        "product_is_identity": false,
        "product_mask": 264,
        "product_named_generator": null,
        "product_sector26_clock_shift_mod26": 16,
        "product_support_generator_ids": [
          3,
          8
        ],
        "right": "P8",
        "right_source_generators": [
          8
        ],
        "shared_source_generators": []
      },
      {
        "clock_defect_mod26": 0,
        "left": "P3",
        "left_source_generators": [
          3
        ],
        "naive_clock_sum_mod26": 0,
        "product_is_identity": false,
        "product_mask": 552,
        "product_named_generator": null,
        "product_sector26_clock_shift_mod26": 0,
        "product_support_generator_ids": [
          3,
          5,
          9
        ],
        "right": "C5_9",
        "right_source_generators": [
          5,
          9
        ],
        "shared_source_generators": []
      },
      {
        "clock_defect_mod26": 0,
        "left": "P3",
        "left_source_generators": [
          3
        ],
        "naive_clock_sum_mod26": 6,
        "product_is_identity": false,
        "product_mask": 1064,
        "product_named_generator": null,
        "product_sector26_clock_shift_mod26": 6,
        "product_support_generator_ids": [
          3,
          5,
          10
        ],
        "right": "C5_10",
        "right_source_generators": [
          5,
          10
        ],
        "shared_source_generators": []
      },
      {
        "clock_defect_mod26": 0,
        "left": "P3",
        "left_source_generators": [
          3
        ],
        "naive_clock_sum_mod26": 0,
        "product_is_identity": false,
        "product_mask": 1544,
        "product_named_generator": null,
        "product_sector26_clock_shift_mod26": 0,
        "product_support_generator_ids": [
          3,
          9,
          10
        ],
        "right": "C9_10",
        "right_source_generators": [
          9,
          10
        ],
        "shared_source_generators": []
      },
      {
        "clock_defect_mod26": 0,
        "left": "P4",
        "left_source_generators": [
          4
        ],
        "naive_clock_sum_mod26": 0,
        "product_is_identity": false,
        "product_mask": 17,
        "product_named_generator": null,
        "product_sector26_clock_shift_mod26": 0,
        "product_support_generator_ids": [
          0,
          4
        ],
        "right": "P0",
        "right_source_generators": [
          0
        ],
        "shared_source_generators": []
      },
      {
        "clock_defect_mod26": 0,
        "left": "P4",
        "left_source_generators": [
          4
        ],
        "naive_clock_sum_mod26": 2,
        "product_is_identity": false,
        "product_mask": 18,
        "product_named_generator": null,
        "product_sector26_clock_shift_mod26": 2,
        "product_support_generator_ids": [
          1,
          4
        ],
        "right": "P1",
        "right_source_generators": [
          1
        ],
        "shared_source_generators": []
      },
      {
        "clock_defect_mod26": 0,
        "left": "P4",
        "left_source_generators": [
          4
        ],
        "naive_clock_sum_mod26": 6,
        "product_is_identity": false,
        "product_mask": 20,
        "product_named_generator": null,
        "product_sector26_clock_shift_mod26": 6,
        "product_support_generator_ids": [
          2,
          4
        ],
        "right": "P2",
        "right_source_generators": [
          2
        ],
        "shared_source_generators": []
      },
      {
        "clock_defect_mod26": 0,
        "left": "P4",
        "left_source_generators": [
          4
        ],
        "naive_clock_sum_mod26": 12,
        "product_is_identity": false,
        "product_mask": 24,
        "product_named_generator": null,
        "product_sector26_clock_shift_mod26": 12,
        "product_support_generator_ids": [
          3,
          4
        ],
        "right": "P3",
        "right_source_generators": [
          3
        ],
        "shared_source_generators": []
      },
      {
        "clock_defect_mod26": 24,
        "left": "P4",
        "left_source_generators": [
          4
        ],
        "naive_clock_sum_mod26": 2,
        "product_is_identity": true,
        "product_mask": 0,
        "product_named_generator": null,
        "product_sector26_clock_shift_mod26": 0,
        "product_support_generator_ids": [],
        "right": "P4",
        "right_source_generators": [
          4
        ],
        "shared_source_generators": [
          4
        ]
      },
      {
        "clock_defect_mod26": 0,
        "left": "P4",
        "left_source_generators": [
          4
        ],
        "naive_clock_sum_mod26": 22,
        "product_is_identity": false,
        "product_mask": 80,
        "product_named_generator": null,
        "product_sector26_clock_shift_mod26": 22,
        "product_support_generator_ids": [
          4,
          6
        ],
        "right": "P6",
        "right_source_generators": [
          6
        ],
        "shared_source_generators": []
      },
      {
        "clock_defect_mod26": 0,
        "left": "P4",
        "left_source_generators": [
          4
        ],
        "naive_clock_sum_mod26": 24,
        "product_is_identity": false,
        "product_mask": 144,
        "product_named_generator": null,
        "product_sector26_clock_shift_mod26": 24,
        "product_support_generator_ids": [
          4,
          7
        ],
        "right": "P7",
        "right_source_generators": [
          7
        ],
        "shared_source_generators": []
      },
      {
        "clock_defect_mod26": 0,
        "left": "P4",
        "left_source_generators": [
          4
        ],
        "naive_clock_sum_mod26": 6,
        "product_is_identity": false,
        "product_mask": 272,
        "product_named_generator": null,
        "product_sector26_clock_shift_mod26": 6,
        "product_support_generator_ids": [
          4,
          8
        ],
        "right": "P8",
        "right_source_generators": [
          8
        ],
        "shared_source_generators": []
      },
      {
        "clock_defect_mod26": 0,
        "left": "P4",
        "left_source_generators": [
          4
        ],
        "naive_clock_sum_mod26": 16,
        "product_is_identity": false,
        "product_mask": 560,
        "product_named_generator": null,
        "product_sector26_clock_shift_mod26": 16,
        "product_support_generator_ids": [
          4,
          5,
          9
        ],
        "right": "C5_9",
        "right_source_generators": [
          5,
          9
        ],
        "shared_source_generators": []
      },
      {
        "clock_defect_mod26": 0,
        "left": "P4",
        "left_source_generators": [
          4
        ],
        "naive_clock_sum_mod26": 22,
        "product_is_identity": false,
        "product_mask": 1072,
        "product_named_generator": null,
        "product_sector26_clock_shift_mod26": 22,
        "product_support_generator_ids": [
          4,
          5,
          10
        ],
        "right": "C5_10",
        "right_source_generators": [
          5,
          10
        ],
        "shared_source_generators": []
      },
      {
        "clock_defect_mod26": 0,
        "left": "P4",
        "left_source_generators": [
          4
        ],
        "naive_clock_sum_mod26": 16,
        "product_is_identity": false,
        "product_mask": 1552,
        "product_named_generator": null,
        "product_sector26_clock_shift_mod26": 16,
        "product_support_generator_ids": [
          4,
          9,
          10
        ],
        "right": "C9_10",
        "right_source_generators": [
          9,
          10
        ],
        "shared_source_generators": []
      },
      {
        "clock_defect_mod26": 0,
        "left": "P6",
        "left_source_generators": [
          6
        ],
        "naive_clock_sum_mod26": 20,
        "product_is_identity": false,
        "product_mask": 65,
        "product_named_generator": null,
        "product_sector26_clock_shift_mod26": 20,
        "product_support_generator_ids": [
          0,
          6
        ],
        "right": "P0",
        "right_source_generators": [
          0
        ],
        "shared_source_generators": []
      },
      {
        "clock_defect_mod26": 0,
        "left": "P6",
        "left_source_generators": [
          6
        ],
        "naive_clock_sum_mod26": 22,
        "product_is_identity": false,
        "product_mask": 66,
        "product_named_generator": null,
        "product_sector26_clock_shift_mod26": 22,
        "product_support_generator_ids": [
          1,
          6
        ],
        "right": "P1",
        "right_source_generators": [
          1
        ],
        "shared_source_generators": []
      },
      {
        "clock_defect_mod26": 0,
        "left": "P6",
        "left_source_generators": [
          6
        ],
        "naive_clock_sum_mod26": 0,
        "product_is_identity": false,
        "product_mask": 68,
        "product_named_generator": null,
        "product_sector26_clock_shift_mod26": 0,
        "product_support_generator_ids": [
          2,
          6
        ],
        "right": "P2",
        "right_source_generators": [
          2
        ],
        "shared_source_generators": []
      },
      {
        "clock_defect_mod26": 0,
        "left": "P6",
        "left_source_generators": [
          6
        ],
        "naive_clock_sum_mod26": 6,
        "product_is_identity": false,
        "product_mask": 72,
        "product_named_generator": null,
        "product_sector26_clock_shift_mod26": 6,
        "product_support_generator_ids": [
          3,
          6
        ],
        "right": "P3",
        "right_source_generators": [
          3
        ],
        "shared_source_generators": []
      },
      {
        "clock_defect_mod26": 0,
        "left": "P6",
        "left_source_generators": [
          6
        ],
        "naive_clock_sum_mod26": 22,
        "product_is_identity": false,
        "product_mask": 80,
        "product_named_generator": null,
        "product_sector26_clock_shift_mod26": 22,
        "product_support_generator_ids": [
          4,
          6
        ],
        "right": "P4",
        "right_source_generators": [
          4
        ],
        "shared_source_generators": []
      },
      {
        "clock_defect_mod26": 10,
        "left": "P6",
        "left_source_generators": [
          6
        ],
        "naive_clock_sum_mod26": 16,
        "product_is_identity": true,
        "product_mask": 0,
        "product_named_generator": null,
        "product_sector26_clock_shift_mod26": 0,
        "product_support_generator_ids": [],
        "right": "P6",
        "right_source_generators": [
          6
        ],
        "shared_source_generators": [
          6
        ]
      },
      {
        "clock_defect_mod26": 0,
        "left": "P6",
        "left_source_generators": [
          6
        ],
        "naive_clock_sum_mod26": 18,
        "product_is_identity": false,
        "product_mask": 192,
        "product_named_generator": null,
        "product_sector26_clock_shift_mod26": 18,
        "product_support_generator_ids": [
          6,
          7
        ],
        "right": "P7",
        "right_source_generators": [
          7
        ],
        "shared_source_generators": []
      },
      {
        "clock_defect_mod26": 0,
        "left": "P6",
        "left_source_generators": [
          6
        ],
        "naive_clock_sum_mod26": 0,
        "product_is_identity": false,
        "product_mask": 320,
        "product_named_generator": null,
        "product_sector26_clock_shift_mod26": 0,
        "product_support_generator_ids": [
          6,
          8
        ],
        "right": "P8",
        "right_source_generators": [
          8
        ],
        "shared_source_generators": []
      },
      {
        "clock_defect_mod26": 0,
        "left": "P6",
        "left_source_generators": [
          6
        ],
        "naive_clock_sum_mod26": 10,
        "product_is_identity": false,
        "product_mask": 608,
        "product_named_generator": null,
        "product_sector26_clock_shift_mod26": 10,
        "product_support_generator_ids": [
          5,
          6,
          9
        ],
        "right": "C5_9",
        "right_source_generators": [
          5,
          9
        ],
        "shared_source_generators": []
      },
      {
        "clock_defect_mod26": 0,
        "left": "P6",
        "left_source_generators": [
          6
        ],
        "naive_clock_sum_mod26": 16,
        "product_is_identity": false,
        "product_mask": 1120,
        "product_named_generator": null,
        "product_sector26_clock_shift_mod26": 16,
        "product_support_generator_ids": [
          5,
          6,
          10
        ],
        "right": "C5_10",
        "right_source_generators": [
          5,
          10
        ],
        "shared_source_generators": []
      },
      {
        "clock_defect_mod26": 0,
        "left": "P6",
        "left_source_generators": [
          6
        ],
        "naive_clock_sum_mod26": 10,
        "product_is_identity": false,
        "product_mask": 1600,
        "product_named_generator": null,
        "product_sector26_clock_shift_mod26": 10,
        "product_support_generator_ids": [
          6,
          9,
          10
        ],
        "right": "C9_10",
        "right_source_generators": [
          9,
          10
        ],
        "shared_source_generators": []
      },
      {
        "clock_defect_mod26": 0,
        "left": "P7",
        "left_source_generators": [
          7
        ],
        "naive_clock_sum_mod26": 22,
        "product_is_identity": false,
        "product_mask": 129,
        "product_named_generator": null,
        "product_sector26_clock_shift_mod26": 22,
        "product_support_generator_ids": [
          0,
          7
        ],
        "right": "P0",
        "right_source_generators": [
          0
        ],
        "shared_source_generators": []
      },
      {
        "clock_defect_mod26": 0,
        "left": "P7",
        "left_source_generators": [
          7
        ],
        "naive_clock_sum_mod26": 24,
        "product_is_identity": false,
        "product_mask": 130,
        "product_named_generator": null,
        "product_sector26_clock_shift_mod26": 24,
        "product_support_generator_ids": [
          1,
          7
        ],
        "right": "P1",
        "right_source_generators": [
          1
        ],
        "shared_source_generators": []
      },
      {
        "clock_defect_mod26": 0,
        "left": "P7",
        "left_source_generators": [
          7
        ],
        "naive_clock_sum_mod26": 2,
        "product_is_identity": false,
        "product_mask": 132,
        "product_named_generator": null,
        "product_sector26_clock_shift_mod26": 2,
        "product_support_generator_ids": [
          2,
          7
        ],
        "right": "P2",
        "right_source_generators": [
          2
        ],
        "shared_source_generators": []
      },
      {
        "clock_defect_mod26": 0,
        "left": "P7",
        "left_source_generators": [
          7
        ],
        "naive_clock_sum_mod26": 8,
        "product_is_identity": false,
        "product_mask": 136,
        "product_named_generator": null,
        "product_sector26_clock_shift_mod26": 8,
        "product_support_generator_ids": [
          3,
          7
        ],
        "right": "P3",
        "right_source_generators": [
          3
        ],
        "shared_source_generators": []
      },
      {
        "clock_defect_mod26": 0,
        "left": "P7",
        "left_source_generators": [
          7
        ],
        "naive_clock_sum_mod26": 24,
        "product_is_identity": false,
        "product_mask": 144,
        "product_named_generator": null,
        "product_sector26_clock_shift_mod26": 24,
        "product_support_generator_ids": [
          4,
          7
        ],
        "right": "P4",
        "right_source_generators": [
          4
        ],
        "shared_source_generators": []
      },
      {
        "clock_defect_mod26": 0,
        "left": "P7",
        "left_source_generators": [
          7
        ],
        "naive_clock_sum_mod26": 18,
        "product_is_identity": false,
        "product_mask": 192,
        "product_named_generator": null,
        "product_sector26_clock_shift_mod26": 18,
        "product_support_generator_ids": [
          6,
          7
        ],
        "right": "P6",
        "right_source_generators": [
          6
        ],
        "shared_source_generators": []
      },
      {
        "clock_defect_mod26": 6,
        "left": "P7",
        "left_source_generators": [
          7
        ],
        "naive_clock_sum_mod26": 20,
        "product_is_identity": true,
        "product_mask": 0,
        "product_named_generator": null,
        "product_sector26_clock_shift_mod26": 0,
        "product_support_generator_ids": [],
        "right": "P7",
        "right_source_generators": [
          7
        ],
        "shared_source_generators": [
          7
        ]
      },
      {
        "clock_defect_mod26": 0,
        "left": "P7",
        "left_source_generators": [
          7
        ],
        "naive_clock_sum_mod26": 2,
        "product_is_identity": false,
        "product_mask": 384,
        "product_named_generator": null,
        "product_sector26_clock_shift_mod26": 2,
        "product_support_generator_ids": [
          7,
          8
        ],
        "right": "P8",
        "right_source_generators": [
          8
        ],
        "shared_source_generators": []
      },
      {
        "clock_defect_mod26": 0,
        "left": "P7",
        "left_source_generators": [
          7
        ],
        "naive_clock_sum_mod26": 12,
        "product_is_identity": false,
        "product_mask": 672,
        "product_named_generator": null,
        "product_sector26_clock_shift_mod26": 12,
        "product_support_generator_ids": [
          5,
          7,
          9
        ],
        "right": "C5_9",
        "right_source_generators": [
          5,
          9
        ],
        "shared_source_generators": []
      },
      {
        "clock_defect_mod26": 0,
        "left": "P7",
        "left_source_generators": [
          7
        ],
        "naive_clock_sum_mod26": 18,
        "product_is_identity": false,
        "product_mask": 1184,
        "product_named_generator": null,
        "product_sector26_clock_shift_mod26": 18,
        "product_support_generator_ids": [
          5,
          7,
          10
        ],
        "right": "C5_10",
        "right_source_generators": [
          5,
          10
        ],
        "shared_source_generators": []
      },
      {
        "clock_defect_mod26": 0,
        "left": "P7",
        "left_source_generators": [
          7
        ],
        "naive_clock_sum_mod26": 12,
        "product_is_identity": false,
        "product_mask": 1664,
        "product_named_generator": null,
        "product_sector26_clock_shift_mod26": 12,
        "product_support_generator_ids": [
          7,
          9,
          10
        ],
        "right": "C9_10",
        "right_source_generators": [
          9,
          10
        ],
        "shared_source_generators": []
      },
      {
        "clock_defect_mod26": 0,
        "left": "P8",
        "left_source_generators": [
          8
        ],
        "naive_clock_sum_mod26": 4,
        "product_is_identity": false,
        "product_mask": 257,
        "product_named_generator": null,
        "product_sector26_clock_shift_mod26": 4,
        "product_support_generator_ids": [
          0,
          8
        ],
        "right": "P0",
        "right_source_generators": [
          0
        ],
        "shared_source_generators": []
      },
      {
        "clock_defect_mod26": 0,
        "left": "P8",
        "left_source_generators": [
          8
        ],
        "naive_clock_sum_mod26": 6,
        "product_is_identity": false,
        "product_mask": 258,
        "product_named_generator": null,
        "product_sector26_clock_shift_mod26": 6,
        "product_support_generator_ids": [
          1,
          8
        ],
        "right": "P1",
        "right_source_generators": [
          1
        ],
        "shared_source_generators": []
      },
      {
        "clock_defect_mod26": 0,
        "left": "P8",
        "left_source_generators": [
          8
        ],
        "naive_clock_sum_mod26": 10,
        "product_is_identity": false,
        "product_mask": 260,
        "product_named_generator": null,
        "product_sector26_clock_shift_mod26": 10,
        "product_support_generator_ids": [
          2,
          8
        ],
        "right": "P2",
        "right_source_generators": [
          2
        ],
        "shared_source_generators": []
      },
      {
        "clock_defect_mod26": 0,
        "left": "P8",
        "left_source_generators": [
          8
        ],
        "naive_clock_sum_mod26": 16,
        "product_is_identity": false,
        "product_mask": 264,
        "product_named_generator": null,
        "product_sector26_clock_shift_mod26": 16,
        "product_support_generator_ids": [
          3,
          8
        ],
        "right": "P3",
        "right_source_generators": [
          3
        ],
        "shared_source_generators": []
      },
      {
        "clock_defect_mod26": 0,
        "left": "P8",
        "left_source_generators": [
          8
        ],
        "naive_clock_sum_mod26": 6,
        "product_is_identity": false,
        "product_mask": 272,
        "product_named_generator": null,
        "product_sector26_clock_shift_mod26": 6,
        "product_support_generator_ids": [
          4,
          8
        ],
        "right": "P4",
        "right_source_generators": [
          4
        ],
        "shared_source_generators": []
      },
      {
        "clock_defect_mod26": 0,
        "left": "P8",
        "left_source_generators": [
          8
        ],
        "naive_clock_sum_mod26": 0,
        "product_is_identity": false,
        "product_mask": 320,
        "product_named_generator": null,
        "product_sector26_clock_shift_mod26": 0,
        "product_support_generator_ids": [
          6,
          8
        ],
        "right": "P6",
        "right_source_generators": [
          6
        ],
        "shared_source_generators": []
      },
      {
        "clock_defect_mod26": 0,
        "left": "P8",
        "left_source_generators": [
          8
        ],
        "naive_clock_sum_mod26": 2,
        "product_is_identity": false,
        "product_mask": 384,
        "product_named_generator": null,
        "product_sector26_clock_shift_mod26": 2,
        "product_support_generator_ids": [
          7,
          8
        ],
        "right": "P7",
        "right_source_generators": [
          7
        ],
        "shared_source_generators": []
      },
      {
        "clock_defect_mod26": 16,
        "left": "P8",
        "left_source_generators": [
          8
        ],
        "naive_clock_sum_mod26": 10,
        "product_is_identity": true,
        "product_mask": 0,
        "product_named_generator": null,
        "product_sector26_clock_shift_mod26": 0,
        "product_support_generator_ids": [],
        "right": "P8",
        "right_source_generators": [
          8
        ],
        "shared_source_generators": [
          8
        ]
      },
      {
        "clock_defect_mod26": 0,
        "left": "P8",
        "left_source_generators": [
          8
        ],
        "naive_clock_sum_mod26": 20,
        "product_is_identity": false,
        "product_mask": 800,
        "product_named_generator": null,
        "product_sector26_clock_shift_mod26": 20,
        "product_support_generator_ids": [
          5,
          8,
          9
        ],
        "right": "C5_9",
        "right_source_generators": [
          5,
          9
        ],
        "shared_source_generators": []
      },
      {
        "clock_defect_mod26": 0,
        "left": "P8",
        "left_source_generators": [
          8
        ],
        "naive_clock_sum_mod26": 0,
        "product_is_identity": false,
        "product_mask": 1312,
        "product_named_generator": null,
        "product_sector26_clock_shift_mod26": 0,
        "product_support_generator_ids": [
          5,
          8,
          10
        ],
        "right": "C5_10",
        "right_source_generators": [
          5,
          10
        ],
        "shared_source_generators": []
      },
      {
        "clock_defect_mod26": 0,
        "left": "P8",
        "left_source_generators": [
          8
        ],
        "naive_clock_sum_mod26": 20,
        "product_is_identity": false,
        "product_mask": 1792,
        "product_named_generator": null,
        "product_sector26_clock_shift_mod26": 20,
        "product_support_generator_ids": [
          8,
          9,
          10
        ],
        "right": "C9_10",
        "right_source_generators": [
          9,
          10
        ],
        "shared_source_generators": []
      },
      {
        "clock_defect_mod26": 0,
        "left": "C5_9",
        "left_source_generators": [
          5,
          9
        ],
        "naive_clock_sum_mod26": 14,
        "product_is_identity": false,
        "product_mask": 545,
        "product_named_generator": null,
        "product_sector26_clock_shift_mod26": 14,
        "product_support_generator_ids": [
          0,
          5,
          9
        ],
        "right": "P0",
        "right_source_generators": [
          0
        ],
        "shared_source_generators": []
      },
      {
        "clock_defect_mod26": 0,
        "left": "C5_9",
        "left_source_generators": [
          5,
          9
        ],
        "naive_clock_sum_mod26": 16,
        "product_is_identity": false,
        "product_mask": 546,
        "product_named_generator": null,
        "product_sector26_clock_shift_mod26": 16,
        "product_support_generator_ids": [
          1,
          5,
          9
        ],
        "right": "P1",
        "right_source_generators": [
          1
        ],
        "shared_source_generators": []
      },
      {
        "clock_defect_mod26": 0,
        "left": "C5_9",
        "left_source_generators": [
          5,
          9
        ],
        "naive_clock_sum_mod26": 20,
        "product_is_identity": false,
        "product_mask": 548,
        "product_named_generator": null,
        "product_sector26_clock_shift_mod26": 20,
        "product_support_generator_ids": [
          2,
          5,
          9
        ],
        "right": "P2",
        "right_source_generators": [
          2
        ],
        "shared_source_generators": []
      },
      {
        "clock_defect_mod26": 0,
        "left": "C5_9",
        "left_source_generators": [
          5,
          9
        ],
        "naive_clock_sum_mod26": 0,
        "product_is_identity": false,
        "product_mask": 552,
        "product_named_generator": null,
        "product_sector26_clock_shift_mod26": 0,
        "product_support_generator_ids": [
          3,
          5,
          9
        ],
        "right": "P3",
        "right_source_generators": [
          3
        ],
        "shared_source_generators": []
      },
      {
        "clock_defect_mod26": 0,
        "left": "C5_9",
        "left_source_generators": [
          5,
          9
        ],
        "naive_clock_sum_mod26": 16,
        "product_is_identity": false,
        "product_mask": 560,
        "product_named_generator": null,
        "product_sector26_clock_shift_mod26": 16,
        "product_support_generator_ids": [
          4,
          5,
          9
        ],
        "right": "P4",
        "right_source_generators": [
          4
        ],
        "shared_source_generators": []
      },
      {
        "clock_defect_mod26": 0,
        "left": "C5_9",
        "left_source_generators": [
          5,
          9
        ],
        "naive_clock_sum_mod26": 10,
        "product_is_identity": false,
        "product_mask": 608,
        "product_named_generator": null,
        "product_sector26_clock_shift_mod26": 10,
        "product_support_generator_ids": [
          5,
          6,
          9
        ],
        "right": "P6",
        "right_source_generators": [
          6
        ],
        "shared_source_generators": []
      },
      {
        "clock_defect_mod26": 0,
        "left": "C5_9",
        "left_source_generators": [
          5,
          9
        ],
        "naive_clock_sum_mod26": 12,
        "product_is_identity": false,
        "product_mask": 672,
        "product_named_generator": null,
        "product_sector26_clock_shift_mod26": 12,
        "product_support_generator_ids": [
          5,
          7,
          9
        ],
        "right": "P7",
        "right_source_generators": [
          7
        ],
        "shared_source_generators": []
      },
      {
        "clock_defect_mod26": 0,
        "left": "C5_9",
        "left_source_generators": [
          5,
          9
        ],
        "naive_clock_sum_mod26": 20,
        "product_is_identity": false,
        "product_mask": 800,
        "product_named_generator": null,
        "product_sector26_clock_shift_mod26": 20,
        "product_support_generator_ids": [
          5,
          8,
          9
        ],
        "right": "P8",
        "right_source_generators": [
          8
        ],
        "shared_source_generators": []
      },
      {
        "clock_defect_mod26": 22,
        "left": "C5_9",
        "left_source_generators": [
          5,
          9
        ],
        "naive_clock_sum_mod26": 4,
        "product_is_identity": true,
        "product_mask": 0,
        "product_named_generator": null,
        "product_sector26_clock_shift_mod26": 0,
        "product_support_generator_ids": [],
        "right": "C5_9",
        "right_source_generators": [
          5,
          9
        ],
        "shared_source_generators": [
          5,
          9
        ]
      },
      {
        "clock_defect_mod26": 18,
        "left": "C5_9",
        "left_source_generators": [
          5,
          9
        ],
        "naive_clock_sum_mod26": 10,
        "product_is_identity": false,
        "product_mask": 1536,
        "product_named_generator": "C9_10",
        "product_sector26_clock_shift_mod26": 2,
        "product_support_generator_ids": [
          9,
          10
        ],
        "right": "C5_10",
        "right_source_generators": [
          5,
          10
        ],
        "shared_source_generators": [
          5
        ]
      },
      {
        "clock_defect_mod26": 4,
        "left": "C5_9",
        "left_source_generators": [
          5,
          9
        ],
        "naive_clock_sum_mod26": 4,
        "product_is_identity": false,
        "product_mask": 1056,
        "product_named_generator": "C5_10",
        "product_sector26_clock_shift_mod26": 8,
        "product_support_generator_ids": [
          5,
          10
        ],
        "right": "C9_10",
        "right_source_generators": [
          9,
          10
        ],
        "shared_source_generators": [
          9
        ]
      },
      {
        "clock_defect_mod26": 0,
        "left": "C5_10",
        "left_source_generators": [
          5,
          10
        ],
        "naive_clock_sum_mod26": 20,
        "product_is_identity": false,
        "product_mask": 1057,
        "product_named_generator": null,
        "product_sector26_clock_shift_mod26": 20,
        "product_support_generator_ids": [
          0,
          5,
          10
        ],
        "right": "P0",
        "right_source_generators": [
          0
        ],
        "shared_source_generators": []
      },
      {
        "clock_defect_mod26": 0,
        "left": "C5_10",
        "left_source_generators": [
          5,
          10
        ],
        "naive_clock_sum_mod26": 22,
        "product_is_identity": false,
        "product_mask": 1058,
        "product_named_generator": null,
        "product_sector26_clock_shift_mod26": 22,
        "product_support_generator_ids": [
          1,
          5,
          10
        ],
        "right": "P1",
        "right_source_generators": [
          1
        ],
        "shared_source_generators": []
      },
      {
        "clock_defect_mod26": 0,
        "left": "C5_10",
        "left_source_generators": [
          5,
          10
        ],
        "naive_clock_sum_mod26": 0,
        "product_is_identity": false,
        "product_mask": 1060,
        "product_named_generator": null,
        "product_sector26_clock_shift_mod26": 0,
        "product_support_generator_ids": [
          2,
          5,
          10
        ],
        "right": "P2",
        "right_source_generators": [
          2
        ],
        "shared_source_generators": []
      },
      {
        "clock_defect_mod26": 0,
        "left": "C5_10",
        "left_source_generators": [
          5,
          10
        ],
        "naive_clock_sum_mod26": 6,
        "product_is_identity": false,
        "product_mask": 1064,
        "product_named_generator": null,
        "product_sector26_clock_shift_mod26": 6,
        "product_support_generator_ids": [
          3,
          5,
          10
        ],
        "right": "P3",
        "right_source_generators": [
          3
        ],
        "shared_source_generators": []
      },
      {
        "clock_defect_mod26": 0,
        "left": "C5_10",
        "left_source_generators": [
          5,
          10
        ],
        "naive_clock_sum_mod26": 22,
        "product_is_identity": false,
        "product_mask": 1072,
        "product_named_generator": null,
        "product_sector26_clock_shift_mod26": 22,
        "product_support_generator_ids": [
          4,
          5,
          10
        ],
        "right": "P4",
        "right_source_generators": [
          4
        ],
        "shared_source_generators": []
      },
      {
        "clock_defect_mod26": 0,
        "left": "C5_10",
        "left_source_generators": [
          5,
          10
        ],
        "naive_clock_sum_mod26": 16,
        "product_is_identity": false,
        "product_mask": 1120,
        "product_named_generator": null,
        "product_sector26_clock_shift_mod26": 16,
        "product_support_generator_ids": [
          5,
          6,
          10
        ],
        "right": "P6",
        "right_source_generators": [
          6
        ],
        "shared_source_generators": []
      },
      {
        "clock_defect_mod26": 0,
        "left": "C5_10",
        "left_source_generators": [
          5,
          10
        ],
        "naive_clock_sum_mod26": 18,
        "product_is_identity": false,
        "product_mask": 1184,
        "product_named_generator": null,
        "product_sector26_clock_shift_mod26": 18,
        "product_support_generator_ids": [
          5,
          7,
          10
        ],
        "right": "P7",
        "right_source_generators": [
          7
        ],
        "shared_source_generators": []
      },
      {
        "clock_defect_mod26": 0,
        "left": "C5_10",
        "left_source_generators": [
          5,
          10
        ],
        "naive_clock_sum_mod26": 0,
        "product_is_identity": false,
        "product_mask": 1312,
        "product_named_generator": null,
        "product_sector26_clock_shift_mod26": 0,
        "product_support_generator_ids": [
          5,
          8,
          10
        ],
        "right": "P8",
        "right_source_generators": [
          8
        ],
        "shared_source_generators": []
      },
      {
        "clock_defect_mod26": 18,
        "left": "C5_10",
        "left_source_generators": [
          5,
          10
        ],
        "naive_clock_sum_mod26": 10,
        "product_is_identity": false,
        "product_mask": 1536,
        "product_named_generator": "C9_10",
        "product_sector26_clock_shift_mod26": 2,
        "product_support_generator_ids": [
          9,
          10
        ],
        "right": "C5_9",
        "right_source_generators": [
          5,
          9
        ],
        "shared_source_generators": [
          5
        ]
      },
      {
        "clock_defect_mod26": 10,
        "left": "C5_10",
        "left_source_generators": [
          5,
          10
        ],
        "naive_clock_sum_mod26": 16,
        "product_is_identity": true,
        "product_mask": 0,
        "product_named_generator": null,
        "product_sector26_clock_shift_mod26": 0,
        "product_support_generator_ids": [],
        "right": "C5_10",
        "right_source_generators": [
          5,
          10
        ],
        "shared_source_generators": [
          5,
          10
        ]
      },
      {
        "clock_defect_mod26": 18,
        "left": "C5_10",
        "left_source_generators": [
          5,
          10
        ],
        "naive_clock_sum_mod26": 10,
        "product_is_identity": false,
        "product_mask": 544,
        "product_named_generator": "C5_9",
        "product_sector26_clock_shift_mod26": 2,
        "product_support_generator_ids": [
          5,
          9
        ],
        "right": "C9_10",
        "right_source_generators": [
          9,
          10
        ],
        "shared_source_generators": [
          10
        ]
      },
      {
        "clock_defect_mod26": 0,
        "left": "C9_10",
        "left_source_generators": [
          9,
          10
        ],
        "naive_clock_sum_mod26": 14,
        "product_is_identity": false,
        "product_mask": 1537,
        "product_named_generator": null,
        "product_sector26_clock_shift_mod26": 14,
        "product_support_generator_ids": [
          0,
          9,
          10
        ],
        "right": "P0",
        "right_source_generators": [
          0
        ],
        "shared_source_generators": []
      },
      {
        "clock_defect_mod26": 0,
        "left": "C9_10",
        "left_source_generators": [
          9,
          10
        ],
        "naive_clock_sum_mod26": 16,
        "product_is_identity": false,
        "product_mask": 1538,
        "product_named_generator": null,
        "product_sector26_clock_shift_mod26": 16,
        "product_support_generator_ids": [
          1,
          9,
          10
        ],
        "right": "P1",
        "right_source_generators": [
          1
        ],
        "shared_source_generators": []
      },
      {
        "clock_defect_mod26": 0,
        "left": "C9_10",
        "left_source_generators": [
          9,
          10
        ],
        "naive_clock_sum_mod26": 20,
        "product_is_identity": false,
        "product_mask": 1540,
        "product_named_generator": null,
        "product_sector26_clock_shift_mod26": 20,
        "product_support_generator_ids": [
          2,
          9,
          10
        ],
        "right": "P2",
        "right_source_generators": [
          2
        ],
        "shared_source_generators": []
      },
      {
        "clock_defect_mod26": 0,
        "left": "C9_10",
        "left_source_generators": [
          9,
          10
        ],
        "naive_clock_sum_mod26": 0,
        "product_is_identity": false,
        "product_mask": 1544,
        "product_named_generator": null,
        "product_sector26_clock_shift_mod26": 0,
        "product_support_generator_ids": [
          3,
          9,
          10
        ],
        "right": "P3",
        "right_source_generators": [
          3
        ],
        "shared_source_generators": []
      },
      {
        "clock_defect_mod26": 0,
        "left": "C9_10",
        "left_source_generators": [
          9,
          10
        ],
        "naive_clock_sum_mod26": 16,
        "product_is_identity": false,
        "product_mask": 1552,
        "product_named_generator": null,
        "product_sector26_clock_shift_mod26": 16,
        "product_support_generator_ids": [
          4,
          9,
          10
        ],
        "right": "P4",
        "right_source_generators": [
          4
        ],
        "shared_source_generators": []
      },
      {
        "clock_defect_mod26": 0,
        "left": "C9_10",
        "left_source_generators": [
          9,
          10
        ],
        "naive_clock_sum_mod26": 10,
        "product_is_identity": false,
        "product_mask": 1600,
        "product_named_generator": null,
        "product_sector26_clock_shift_mod26": 10,
        "product_support_generator_ids": [
          6,
          9,
          10
        ],
        "right": "P6",
        "right_source_generators": [
          6
        ],
        "shared_source_generators": []
      },
      {
        "clock_defect_mod26": 0,
        "left": "C9_10",
        "left_source_generators": [
          9,
          10
        ],
        "naive_clock_sum_mod26": 12,
        "product_is_identity": false,
        "product_mask": 1664,
        "product_named_generator": null,
        "product_sector26_clock_shift_mod26": 12,
        "product_support_generator_ids": [
          7,
          9,
          10
        ],
        "right": "P7",
        "right_source_generators": [
          7
        ],
        "shared_source_generators": []
      },
      {
        "clock_defect_mod26": 0,
        "left": "C9_10",
        "left_source_generators": [
          9,
          10
        ],
        "naive_clock_sum_mod26": 20,
        "product_is_identity": false,
        "product_mask": 1792,
        "product_named_generator": null,
        "product_sector26_clock_shift_mod26": 20,
        "product_support_generator_ids": [
          8,
          9,
          10
        ],
        "right": "P8",
        "right_source_generators": [
          8
        ],
        "shared_source_generators": []
      },
      {
        "clock_defect_mod26": 4,
        "left": "C9_10",
        "left_source_generators": [
          9,
          10
        ],
        "naive_clock_sum_mod26": 4,
        "product_is_identity": false,
        "product_mask": 1056,
        "product_named_generator": "C5_10",
        "product_sector26_clock_shift_mod26": 8,
        "product_support_generator_ids": [
          5,
          10
        ],
        "right": "C5_9",
        "right_source_generators": [
          5,
          9
        ],
        "shared_source_generators": [
          9
        ]
      },
      {
        "clock_defect_mod26": 18,
        "left": "C9_10",
        "left_source_generators": [
          9,
          10
        ],
        "naive_clock_sum_mod26": 10,
        "product_is_identity": false,
        "product_mask": 544,
        "product_named_generator": "C5_9",
        "product_sector26_clock_shift_mod26": 2,
        "product_support_generator_ids": [
          5,
          9
        ],
        "right": "C5_10",
        "right_source_generators": [
          5,
          10
        ],
        "shared_source_generators": [
          10
        ]
      },
      {
        "clock_defect_mod26": 22,
        "left": "C9_10",
        "left_source_generators": [
          9,
          10
        ],
        "naive_clock_sum_mod26": 4,
        "product_is_identity": true,
        "product_mask": 0,
        "product_named_generator": null,
        "product_sector26_clock_shift_mod26": 0,
        "product_support_generator_ids": [],
        "right": "C9_10",
        "right_source_generators": [
          9,
          10
        ],
        "shared_source_generators": [
          9,
          10
        ]
      }
    ],
    "generator_multiplication_table_sha256": "d6c76aeb0b3577a7e79f73923c5e1e8ce6da6354888ec2987302a0be2d00536c",
    "generator_rows": [
      {
        "corrected_hidden_clock_shift_mod26": 13,
        "generator_label": "P0",
        "generator_type": "primitive_preserving",
        "operator_mask": 1,
        "sector26_clock_shift_mod26": 12,
        "source_generators": [
          0
        ],
        "support_generator_ids": [
          0
        ]
      },
      {
        "corrected_hidden_clock_shift_mod26": 13,
        "generator_label": "P1",
        "generator_type": "primitive_preserving",
        "operator_mask": 2,
        "sector26_clock_shift_mod26": 14,
        "source_generators": [
          1
        ],
        "support_generator_ids": [
          1
        ]
      },
      {
        "corrected_hidden_clock_shift_mod26": 13,
        "generator_label": "P2",
        "generator_type": "primitive_preserving",
        "operator_mask": 4,
        "sector26_clock_shift_mod26": 18,
        "source_generators": [
          2
        ],
        "support_generator_ids": [
          2
        ]
      },
      {
        "corrected_hidden_clock_shift_mod26": 0,
        "generator_label": "P3",
        "generator_type": "primitive_preserving",
        "operator_mask": 8,
        "sector26_clock_shift_mod26": 24,
        "source_generators": [
          3
        ],
        "support_generator_ids": [
          3
        ]
      },
      {
        "corrected_hidden_clock_shift_mod26": 13,
        "generator_label": "P4",
        "generator_type": "primitive_preserving",
        "operator_mask": 16,
        "sector26_clock_shift_mod26": 14,
        "source_generators": [
          4
        ],
        "support_generator_ids": [
          4
        ]
      },
      {
        "corrected_hidden_clock_shift_mod26": 13,
        "generator_label": "P6",
        "generator_type": "primitive_preserving",
        "operator_mask": 64,
        "sector26_clock_shift_mod26": 8,
        "source_generators": [
          6
        ],
        "support_generator_ids": [
          6
        ]
      },
      {
        "corrected_hidden_clock_shift_mod26": 13,
        "generator_label": "P7",
        "generator_type": "primitive_preserving",
        "operator_mask": 128,
        "sector26_clock_shift_mod26": 10,
        "source_generators": [
          7
        ],
        "support_generator_ids": [
          7
        ]
      },
      {
        "corrected_hidden_clock_shift_mod26": 13,
        "generator_label": "P8",
        "generator_type": "primitive_preserving",
        "operator_mask": 256,
        "sector26_clock_shift_mod26": 18,
        "source_generators": [
          8
        ],
        "support_generator_ids": [
          8
        ]
      },
      {
        "corrected_hidden_clock_shift_mod26": 0,
        "generator_label": "C5_9",
        "generator_type": "paired_cross_return_composite",
        "operator_mask": 544,
        "sector26_clock_shift_mod26": 2,
        "source_generators": [
          5,
          9
        ],
        "support_generator_ids": [
          5,
          9
        ]
      },
      {
        "corrected_hidden_clock_shift_mod26": 0,
        "generator_label": "C5_10",
        "generator_type": "paired_cross_return_composite",
        "operator_mask": 1056,
        "sector26_clock_shift_mod26": 8,
        "source_generators": [
          5,
          10
        ],
        "support_generator_ids": [
          5,
          10
        ]
      },
      {
        "corrected_hidden_clock_shift_mod26": 0,
        "generator_label": "C9_10",
        "generator_type": "paired_cross_return_composite",
        "operator_mask": 1536,
        "sector26_clock_shift_mod26": 2,
        "source_generators": [
          9,
          10
        ],
        "support_generator_ids": [
          9,
          10
        ]
      }
    ],
    "generator_rows_sha256": "115c9048103e4204a69a026c5a2da4cd5db9ce21a1587c73753f4e7b995902e7",
    "sector26_clock_defect_rows": [
      {
        "clock_defect_mod26": 2,
        "left": "P0",
        "left_source_generators": [
          0
        ],
        "naive_clock_sum_mod26": 24,
        "product_is_identity": true,
        "product_mask": 0,
        "product_named_generator": null,
        "product_sector26_clock_shift_mod26": 0,
        "product_support_generator_ids": [],
        "right": "P0",
        "right_source_generators": [
          0
        ],
        "shared_source_generators": [
          0
        ]
      },
      {
        "clock_defect_mod26": 24,
        "left": "P1",
        "left_source_generators": [
          1
        ],
        "naive_clock_sum_mod26": 2,
        "product_is_identity": true,
        "product_mask": 0,
        "product_named_generator": null,
        "product_sector26_clock_shift_mod26": 0,
        "product_support_generator_ids": [],
        "right": "P1",
        "right_source_generators": [
          1
        ],
        "shared_source_generators": [
          1
        ]
      },
      {
        "clock_defect_mod26": 16,
        "left": "P2",
        "left_source_generators": [
          2
        ],
        "naive_clock_sum_mod26": 10,
        "product_is_identity": true,
        "product_mask": 0,
        "product_named_generator": null,
        "product_sector26_clock_shift_mod26": 0,
        "product_support_generator_ids": [],
        "right": "P2",
        "right_source_generators": [
          2
        ],
        "shared_source_generators": [
          2
        ]
      },
      {
        "clock_defect_mod26": 4,
        "left": "P3",
        "left_source_generators": [
          3
        ],
        "naive_clock_sum_mod26": 22,
        "product_is_identity": true,
        "product_mask": 0,
        "product_named_generator": null,
        "product_sector26_clock_shift_mod26": 0,
        "product_support_generator_ids": [],
        "right": "P3",
        "right_source_generators": [
          3
        ],
        "shared_source_generators": [
          3
        ]
      },
      {
        "clock_defect_mod26": 24,
        "left": "P4",
        "left_source_generators": [
          4
        ],
        "naive_clock_sum_mod26": 2,
        "product_is_identity": true,
        "product_mask": 0,
        "product_named_generator": null,
        "product_sector26_clock_shift_mod26": 0,
        "product_support_generator_ids": [],
        "right": "P4",
        "right_source_generators": [
          4
        ],
        "shared_source_generators": [
          4
        ]
      },
      {
        "clock_defect_mod26": 10,
        "left": "P6",
        "left_source_generators": [
          6
        ],
        "naive_clock_sum_mod26": 16,
        "product_is_identity": true,
        "product_mask": 0,
        "product_named_generator": null,
        "product_sector26_clock_shift_mod26": 0,
        "product_support_generator_ids": [],
        "right": "P6",
        "right_source_generators": [
          6
        ],
        "shared_source_generators": [
          6
        ]
      },
      {
        "clock_defect_mod26": 6,
        "left": "P7",
        "left_source_generators": [
          7
        ],
        "naive_clock_sum_mod26": 20,
        "product_is_identity": true,
        "product_mask": 0,
        "product_named_generator": null,
        "product_sector26_clock_shift_mod26": 0,
        "product_support_generator_ids": [],
        "right": "P7",
        "right_source_generators": [
          7
        ],
        "shared_source_generators": [
          7
        ]
      },
      {
        "clock_defect_mod26": 16,
        "left": "P8",
        "left_source_generators": [
          8
        ],
        "naive_clock_sum_mod26": 10,
        "product_is_identity": true,
        "product_mask": 0,
        "product_named_generator": null,
        "product_sector26_clock_shift_mod26": 0,
        "product_support_generator_ids": [],
        "right": "P8",
        "right_source_generators": [
          8
        ],
        "shared_source_generators": [
          8
        ]
      },
      {
        "clock_defect_mod26": 22,
        "left": "C5_9",
        "left_source_generators": [
          5,
          9
        ],
        "naive_clock_sum_mod26": 4,
        "product_is_identity": true,
        "product_mask": 0,
        "product_named_generator": null,
        "product_sector26_clock_shift_mod26": 0,
        "product_support_generator_ids": [],
        "right": "C5_9",
        "right_source_generators": [
          5,
          9
        ],
        "shared_source_generators": [
          5,
          9
        ]
      },
      {
        "clock_defect_mod26": 18,
        "left": "C5_9",
        "left_source_generators": [
          5,
          9
        ],
        "naive_clock_sum_mod26": 10,
        "product_is_identity": false,
        "product_mask": 1536,
        "product_named_generator": "C9_10",
        "product_sector26_clock_shift_mod26": 2,
        "product_support_generator_ids": [
          9,
          10
        ],
        "right": "C5_10",
        "right_source_generators": [
          5,
          10
        ],
        "shared_source_generators": [
          5
        ]
      },
      {
        "clock_defect_mod26": 4,
        "left": "C5_9",
        "left_source_generators": [
          5,
          9
        ],
        "naive_clock_sum_mod26": 4,
        "product_is_identity": false,
        "product_mask": 1056,
        "product_named_generator": "C5_10",
        "product_sector26_clock_shift_mod26": 8,
        "product_support_generator_ids": [
          5,
          10
        ],
        "right": "C9_10",
        "right_source_generators": [
          9,
          10
        ],
        "shared_source_generators": [
          9
        ]
      },
      {
        "clock_defect_mod26": 18,
        "left": "C5_10",
        "left_source_generators": [
          5,
          10
        ],
        "naive_clock_sum_mod26": 10,
        "product_is_identity": false,
        "product_mask": 1536,
        "product_named_generator": "C9_10",
        "product_sector26_clock_shift_mod26": 2,
        "product_support_generator_ids": [
          9,
          10
        ],
        "right": "C5_9",
        "right_source_generators": [
          5,
          9
        ],
        "shared_source_generators": [
          5
        ]
      },
      {
        "clock_defect_mod26": 10,
        "left": "C5_10",
        "left_source_generators": [
          5,
          10
        ],
        "naive_clock_sum_mod26": 16,
        "product_is_identity": true,
        "product_mask": 0,
        "product_named_generator": null,
        "product_sector26_clock_shift_mod26": 0,
        "product_support_generator_ids": [],
        "right": "C5_10",
        "right_source_generators": [
          5,
          10
        ],
        "shared_source_generators": [
          5,
          10
        ]
      },
      {
        "clock_defect_mod26": 18,
        "left": "C5_10",
        "left_source_generators": [
          5,
          10
        ],
        "naive_clock_sum_mod26": 10,
        "product_is_identity": false,
        "product_mask": 544,
        "product_named_generator": "C5_9",
        "product_sector26_clock_shift_mod26": 2,
        "product_support_generator_ids": [
          5,
          9
        ],
        "right": "C9_10",
        "right_source_generators": [
          9,
          10
        ],
        "shared_source_generators": [
          10
        ]
      },
      {
        "clock_defect_mod26": 4,
        "left": "C9_10",
        "left_source_generators": [
          9,
          10
        ],
        "naive_clock_sum_mod26": 4,
        "product_is_identity": false,
        "product_mask": 1056,
        "product_named_generator": "C5_10",
        "product_sector26_clock_shift_mod26": 8,
        "product_support_generator_ids": [
          5,
          10
        ],
        "right": "C5_9",
        "right_source_generators": [
          5,
          9
        ],
        "shared_source_generators": [
          9
        ]
      },
      {
        "clock_defect_mod26": 18,
        "left": "C9_10",
        "left_source_generators": [
          9,
          10
        ],
        "naive_clock_sum_mod26": 10,
        "product_is_identity": false,
        "product_mask": 544,
        "product_named_generator": "C5_9",
        "product_sector26_clock_shift_mod26": 2,
        "product_support_generator_ids": [
          5,
          9
        ],
        "right": "C5_10",
        "right_source_generators": [
          5,
          10
        ],
        "shared_source_generators": [
          10
        ]
      },
      {
        "clock_defect_mod26": 22,
        "left": "C9_10",
        "left_source_generators": [
          9,
          10
        ],
        "naive_clock_sum_mod26": 4,
        "product_is_identity": true,
        "product_mask": 0,
        "product_named_generator": null,
        "product_sector26_clock_shift_mod26": 0,
        "product_support_generator_ids": [],
        "right": "C9_10",
        "right_source_generators": [
          9,
          10
        ],
        "shared_source_generators": [
          9,
          10
        ]
      }
    ],
    "sector26_clock_defect_rows_sha256": "fb0fa8c088e002edb5bcc5d443752c9246dcc735d91986a2572f44f1771cb321"
  },
  "inputs": {
    "amplitude_quotient_fourier_mode_classifier_report": {
      "path": "data/invariants/d20/theorems/amplitude_quotient_fourier_mode_classifier/report.json",
      "sha256": "cc4b2b3cd08f45339f5d72e66ff7acb6e75b7ddad51672756736a23ecd24599a"
    },
    "finite_virasoro_string_kernel_candidate_report": {
      "path": "data/invariants/d20/theorems/finite_virasoro_string_kernel_candidate/report.json",
      "sha256": "fd547abff233b095ca27c611d7cf126f0d06fd76618ca9b8af6c85cf016a91b5"
    }
  },
  "interpretation": {
    "what_this_does_not_prove": "This is not yet a noncommutative Virasoro algebra. It certifies the finite translation generator layer and a finite sector-26 clock defect. A Virasoro-like central term or anomaly cocycle must be tested next.",
    "what_this_proves": [
      "the finite string-kernel candidate has a closed rank-10 translation operator algebra",
      "the named internal moves generate all 1024 kernel translations",
      "all named generator commutators vanish at this finite translation layer",
      "the three paired cross-return composites have exactly one dependency: C5_9 C5_10 C9_10 = 1",
      "the sector-26 clock remains even on the kernel and its generator-product defect is localized to overlap cancellation"
    ]
  },
  "next_highest_yield_item": "Test finite central-extension/anomaly cocycles on the generator algebra: search alternating 2-cocycles compatible with the sector-26 clock and identify whether any nontrivial central term survives.",
  "object": "d20",
  "schema": "d20.theorem.finite_virasoro_generator_algebra",
  "status": "D20_FINITE_VIRASORO_GENERATOR_ALGEBRA_CERTIFIED"
}
